{"content": "Yes, Democrats are almost as beholden to corporate special interests as their Republican counterparts, but that\u2019s because they\u2019re playing catchup. It was Republicans that pushed through the bills that unshackled lobbyists and lifted limits on corporate campaign contributions. It was the conservative majority on the Supreme Court that upheld Citizens United. And nothing the modern Democratic Party has done comes close to the conniving voter disenfranchisement efforts that Republicans continue to pursue. From draconian voter ID laws and a racially-biased criminal justice system, to electoral district gerrymandering, the GOP has cemented an unfair advantage that makes it very difficult for Democrats to compete at the polls. All this, despite Democrats advocating legislative policy that is demonstrably fairer and measurably better for the vast majority of people, than that offered by Republicans.", "child": "", "name": "413_5", "parent": "413", "title": ""}