{"b": "28586-6143d83", "v": 3, "payload": {"references": {"Collection": {"b230ea2a6eb8": {"collectionFeatures": [13], "facebookPageName": "TheMissionInc", "description": "Your #1 Source for Accelerated Learning", "instantArticlesState": 0, "header": {"layout": 5, "alignment": 2, "logoImage": {"originalHeight": 424, "originalWidth": 2048, "alt": "The Mission", "id": "1*yXjgGzgQdj_0wCMVrqFFuA@2x.png"}, "backgroundImage": {}}, "favicon": {"originalHeight": 0, "originalWidth": 0, "imageId": "", "height": 0, "filter": "", "width": 0, "strategy": "resample", "backgroundSize": ""}, "publicEmail": "Stephanie@TheMission.co", "name": "The Mission", "image": {"originalHeight": 180, "originalWidth": 180, "imageId": "1*lweRCs77VRPCrZvX8Sv-Jg.png", "height": 0, "filter": "", "width": 0, "strategy": "resample", "backgroundSize": ""}, "shortDescription": "Your #1 Source for Accelerated Learning", "collectionMastheadId": "c8aef899c6d5", "navItems": [{"title": "Newsletter", "url": "https://medium.com/the-mission/build-your-reputation-but-dont-be-afraid-to-destroy-it-and-become-notorious-ad6223ec2a05", "source": "postId", "postId": "ad6223ec2a05", "type": 2}, {"title": "Life & Health", "source": "tagSlug", "tagSlug": "life", "url": "https://medium.com/the-mission/tagged/life", "type": 1}, {"title": "Tech & Business", "source": "tagSlug", "tagSlug": "tech", "url": "https://medium.com/the-mission/tagged/tech", "type": 1}, {"title": "Science & Makers", "source": "tagSlug", "tagSlug": "science", "url": "https://medium.com/the-mission/tagged/science", "type": 1}, {"title": "Art & Design", "source": "tagSlug", "tagSlug": "photography", "url": "https://medium.com/the-mission/tagged/photography", "type": 1}, {"title": "Advertise", "url": "https://the-mission.typeform.com/to/oMGHX6", "type": 3}], "type": "Collection", "logo": {"originalHeight": 212, "originalWidth": 1024, "imageId": "1*EwUITd_m5xd4mPXGs8ANdQ.png", "height": 0, "filter": "", "width": 0, "strategy": "resample", "backgroundSize": ""}, "ampLogo": {"originalHeight": 0, "originalWidth": 0, "imageId": "", "height": 0, "filter": "", "width": 0, "strategy": "resample", "backgroundSize": ""}, "creatorId": "8804c3026cce", "colorBehavior": 1, "slug": "the-mission", "tags": ["TECH", "ENTREPRENEURSHIP", "STARTUP", "LIFE", "LIFE LESSONS"], "metadata": {"postCount": 2180, "activeAt": 1492162262681, "followerCount": 269454}, "sections": [{"collectionHeaderMetadata": {"layout": 5, "alignment": 2, "logoImage": {"originalHeight": 424, "originalWidth": 2048, "alt": "The Mission", "id": "1*yXjgGzgQdj_0wCMVrqFFuA@2x.png"}, "backgroundImage": {}}, "type": 2}, {"postListMetadata": {"number": 7, "source": 1, "layout": 7, "postIds": []}, "type": 1}, {"postListMetadata": {"number": 25, "source": 2, "layout": 4, "sectionHeader": "Trending", "postIds": []}, "type": 1}, {"postListMetadata": {"number": 24, "source": 2, "layout": 4, "postIds": []}, "type": 1}, {"postListMetadata": {"number": 8, "source": 3, "layout": 4, "postIds": ["d6a8320bf712", "9db8b5f86db6", "f93d5a3b1309", "abc5cb9129e3", "f61e7578af7d", "a2c3972806ac", "84854eba5f13"]}, "type": 1}, {"postListMetadata": {"number": 23, "source": 1, "layout": 4, "sectionHeader": "Latest", "postIds": []}, "type": 1}, {"postListMetadata": {"number": 8, "source": 1, "layout": 4, "postIds": []}, "type": 1}], "id": "b230ea2a6eb8", "twitterUsername": "TheMissionT", "colorPalette": {"defaultBackgroundSpectrum": {"colorPoints": [{"point": 0, "color": "#FF02B875"}, {"point": 0.1, "color": "#FF00AB6B"}, {"point": 0.2, "color": "#FF1C9963"}, {"point": 1, "color": "#FF092E20"}], "backgroundColor": "#FFFFFFFF"}, "highlightSpectrum": {"colorPoints": [{"point": 0, "color": "#FFFFFFFF"}, {"point": 0.1, "color": "#FFE9FDF0"}, {"point": 0.2, "color": "#FFE2FAEE"}, {"point": 0.6, "color": "#FFADFFCF"}, {"point": 1, "color": "#FF7DFFB3"}], "backgroundColor": "#FFFFFFFF"}}, "acceleratedMobilePagesState": 0, "virtuals": {"isSubscribed": false, "permissions": {"canAddWriters": false, "canSubmit": false, "canEditOwnPosts": false, "canSendNewsletter": false, "canBeAssignedAuthor": false, "canRepublish": false, "canManageAll": false, "canViewLockedPosts": false, "canRemove": false, "canPublishAll": false, "canViewCloaked": false, "canEditPosts": false, "canPublish": false, "canViewStats": false}, "isNewsletterSubscribed": false, "memberOfMembershipPlanId": ""}}}, "Quote": {"616607a75b7a": {"quoteId": "616607a75b7a", "type": "Quote", "endOffset": 398, "startOffset": 0, "quoteType": 1, "paragraphs": [{"layout": 1, "name": "ecab", "href": "", "dataId": "", "purpose": 1, "hasDropCap": false, "translationStatus": 1, "text": "Side-note: Well what about Medium? The more I use Medium, the more I don\u2019t think it counts as a social network. Why? Because in my last two articles, none of the comments were negative or confrontational. Zero. There were several people who wanted to have constructive debates, which is always warmly welcomed! This type of civility isn\u2019t a characteristic of previous social networks and platforms.", "alignment": 1, "markups": [], "type": 1}], "createdAt": 1482201708096, "postId": "6cb23738f823", "userId": "f42556cd052b", "removedAt": 0}, "87e7540e2b86": {"quoteId": "87e7540e2b86", "type": "Quote", "endOffset": 122, "startOffset": 0, "quoteType": 1, "paragraphs": [{"text": "There are even studies that suggest you don\u2019t have to be too picky about the music you select, so long as it\u2019s symphonies.", "name": "6a00", "markups": [], "type": 1}], "createdAt": 1482680040510, "postId": "6cb23738f823", "userId": "7fd8b4b65d69", "removedAt": 0}}, "Post": {"640c6d779e0e": {"importedPublishedAt": 0, "inResponseToPostId": "6cb23738f823", "notifyFollowers": true, "seriesLastAppendedAt": 0, "translationSourceCreatorId": "", "displayAuthor": "", "isTitleSynthesized": true, "detectedLanguage": "en", "license": 0, "id": "640c6d779e0e", "createdAt": 1481673733115, "inResponseToRemovedAt": 0, "isRequestToPubDisabled": false, "responseHiddenOnParentPostAt": 0, "newsletterId": "", "title": "I have been lamenting the end of Season 1 of Westworld\u2026 but discovering that the music can be the\u2026", "slug": "i-have-been-lamenting-the-end-of-season-1-of-westworld-but-discovering-that-the-music-can-be-the", "versionId": "ed44d49dff91", "inResponseToMediaResourceId": "3a040e50cca709732cc42071e7c43389", "isSubscriptionLocked": false, "updatedAt": 1481673834474, "mediumUrl": "", "previewContent": {"bodyModel": {"sections": [{"startIndex": 0}], "paragraphs": [{"text": "I have been lamenting the end of Season 1 of Westworld\u2026 but discovering that the music can be the soundtrack to my day makes the mid work week just a touch more thrilling! Thanks :)", "name": "6126", "alignment": 1, "markups": [], "type": 1}]}, "isFullContent": true}, "webCanonicalUrl": "", "notifyFacebook": false, "experimentalCss": "", "virtuals": {"links": {"entries": [], "generatedAt": 1481673833510, "version": "0.3"}, "imageCount": 0, "socialRecommendsCount": 0, "wordCount": 35, "totalClapCount": 0, "responsesCreatedCount": 0, "isLockedPreviewOnly": false, "usersBySocialRecommends": [], "isBookmarked": false, "recommends": 1, "subtitle": "", "takeoverId": "", "metaDescription": "", "previewImage": {"originalHeight": 0, "originalWidth": 0, "imageId": "", "height": 0, "filter": "", "width": 0, "strategy": "resample", "backgroundSize": ""}, "readingTime": 0.1320754716981132, "allowNotes": true, "tags": []}, "allowResponses": true, "homeCollectionId": "", "isSponsored": false, "importedUrl": "", "vote": false, "acceptedAt": 0, "firstPublishedAt": 1481673833033, "approvedHomeCollectionId": "", "type": "Post", "latestRev": 23, "content": {"postDisplay": {"coverless": true}}, "latestPublishedVersion": "ed44d49dff91", "hasUnpublishedEdits": false, "notifyTwitter": false, "isApprovedTranslation": false, "creatorId": "38e4819c46e8", "visibility": 0, "translationSourcePostId": "", "latestPublishedAt": 1481673833033, "canonicalUrl": "", "coverless": true, "migrationId": "", "uniqueSlug": "i-have-been-lamenting-the-end-of-season-1-of-westworld-but-discovering-that-the-music-can-be-the-640c6d779e0e", "latestVersion": "ed44d49dff91", "isSeries": false}, "9cae348bdef4": {"importedPublishedAt": 0, "inResponseToPostId": "6cb23738f823", "notifyFollowers": true, "seriesLastAppendedAt": 0, "translationSourceCreatorId": "", "displayAuthor": "", "isTitleSynthesized": true, "detectedLanguage": "en", "license": 0, "id": "9cae348bdef4", "createdAt": 1482356622431, "inResponseToRemovedAt": 0, "isRequestToPubDisabled": false, "responseHiddenOnParentPostAt": 0, "newsletterId": "", "title": "It was a pleasure to read it Chad ! Well said , have a great peace in yourself .", "slug": "it-was-a-pleasure-to-read-it-chad-well-said-have-a-great-peace-in-yourself", "versionId": "642a16228162", "inResponseToMediaResourceId": "3a040e50cca709732cc42071e7c43389", "isSubscriptionLocked": false, "updatedAt": 1482356691682, "mediumUrl": "", "previewContent": {"bodyModel": {"sections": [{"startIndex": 0}], "paragraphs": [{"text": "It was a pleasure to read it Chad ! Well said , have a great peace in yourself .", "name": "cb95", "alignment": 1, "markups": [], "type": 1}]}, "isFullContent": true}, "webCanonicalUrl": "", "notifyFacebook": false, "experimentalCss": "", "virtuals": {"links": {"entries": [], "generatedAt": 1482356691346, "version": "0.3"}, "imageCount": 0, "socialRecommendsCount": 0, "wordCount": 19, "totalClapCount": 0, "responsesCreatedCount": 0, "isLockedPreviewOnly": false, "usersBySocialRecommends": [], "isBookmarked": false, "recommends": 1, "subtitle": "", "takeoverId": "", "metaDescription": "", "previewImage": {"originalHeight": 0, "originalWidth": 0, "imageId": "", "height": 0, "filter": "", "width": 0, "strategy": "resample", "backgroundSize": ""}, "readingTime": 0.07169811320754717, "allowNotes": true, "tags": []}, "allowResponses": true, "homeCollectionId": "", "isSponsored": false, "importedUrl": "", "vote": false, "acceptedAt": 0, "firstPublishedAt": 1482356690962, "approvedHomeCollectionId": "", "type": "Post", "latestRev": 12, "content": {"postDisplay": {"coverless": true}}, "latestPublishedVersion": "642a16228162", "hasUnpublishedEdits": false, "notifyTwitter": false, "isApprovedTranslation": false, "creatorId": "24c6d2541429", "visibility": 0, "translationSourcePostId": "", "latestPublishedAt": 1482356690962, "canonicalUrl": "", "coverless": true, "migrationId": "", "uniqueSlug": "it-was-a-pleasure-to-read-it-chad-well-said-have-a-great-peace-in-yourself-9cae348bdef4", "latestVersion": "642a16228162", "isSeries": false}, "174139bb34f4": {"importedPublishedAt": 0, "inResponseToPostId": "6cb23738f823", "notifyFollowers": true, "seriesLastAppendedAt": 0, "translationSourceCreatorId": "", "displayAuthor": "", "isTitleSynthesized": true, "detectedLanguage": "en", "license": 0, "id": "174139bb34f4", "createdAt": 1482093224824, "inResponseToRemovedAt": 0, "isRequestToPubDisabled": false, "responseHiddenOnParentPostAt": 0, "newsletterId": "", "title": "Loved this article, thank you.", "slug": "loved-this-article-thank-you", "versionId": "5146abbb1655", "inResponseToMediaResourceId": "3a040e50cca709732cc42071e7c43389", "isSubscriptionLocked": false, "updatedAt": 1482093866198, "mediumUrl": "", "previewContent": {"bodyModel": {"sections": [{"startIndex": 0}], "paragraphs": [{"text": "Loved this article, thank you. After a post-election mental break-down where I was stuck to social media like gum to a shoe, I turned completely off, turned off news, meditated, moved and listened to music. I realized what a truly unconscious life I\u2019d been living\u2026eating in front of a computer, TV, drinking too much alcohol and caffeine, speaking too\u2026", "name": "bfa2", "alignment": 1, "markups": [], "type": 1}]}, "isFullContent": false}, "webCanonicalUrl": "", "notifyFacebook": false, "experimentalCss": "", "virtuals": {"links": {"entries": [], "generatedAt": 1482093865333, "version": "0.3"}, "imageCount": 0, "socialRecommendsCount": 0, "wordCount": 153, "totalClapCount": 0, "responsesCreatedCount": 0, "isLockedPreviewOnly": false, "usersBySocialRecommends": [], "isBookmarked": false, "recommends": 2, "subtitle": "", "takeoverId": "", "metaDescription": "", "previewImage": {"originalHeight": 0, "originalWidth": 0, "imageId": "", "height": 0, "filter": "", "width": 0, "strategy": "resample", "backgroundSize": ""}, "readingTime": 0.5773584905660377, "allowNotes": true, "tags": [{"name": "Meditation", "slug": "meditation", "metadata": {"coverImage": {"originalHeight": 4320, "originalWidth": 2432, "id": "1*AYeg1JmibQTqTVJt6ElJjQ.jpeg"}, "postCount": 5714, "followerCount": 1213}, "postCount": 5714, "type": "Tag", "virtuals": {"isFollowing": false}}]}, "allowResponses": true, "homeCollectionId": "", "isSponsored": false, "importedUrl": "", "vote": false, "acceptedAt": 0, "firstPublishedAt": 1482093865060, "approvedHomeCollectionId": "", "type": "Post", "latestRev": 113, "content": {"postDisplay": {"coverless": true}}, "latestPublishedVersion": "5146abbb1655", "hasUnpublishedEdits": false, "notifyTwitter": false, "isApprovedTranslation": false, "creatorId": "19236a61f819", "visibility": 0, "translationSourcePostId": "", "latestPublishedAt": 1482093865060, "canonicalUrl": "", "coverless": true, "migrationId": "", "uniqueSlug": "loved-this-article-thank-you-174139bb34f4", "latestVersion": "5146abbb1655", "isSeries": false}, "c8cba35f08da": {"importedPublishedAt": 0, "inResponseToPostId": "e9482caf67be", "notifyFollowers": true, "seriesLastAppendedAt": 0, "translationSourceCreatorId": "", "displayAuthor": "", "isTitleSynthesized": true, "detectedLanguage": "en", "license": 0, "id": "c8cba35f08da", "createdAt": 1481587534938, "inResponseToRemovedAt": 0, "isRequestToPubDisabled": false, "responseHiddenOnParentPostAt": 0, "newsletterId": "", "title": "Of course, glad you enjoyed it Mitzi!", "slug": "of-course-glad-you-enjoyed-it-mitzi", "versionId": "d10f39a36f73", "inResponseToMediaResourceId": "e90896d934f9f0eac32d13cbe577934a", "isSubscriptionLocked": false, "updatedAt": 1481587559993, "mediumUrl": "", "previewContent": {"bodyModel": {"sections": [{"startIndex": 0}], "paragraphs": [{"text": "Of course, glad you enjoyed it Mitzi!", "name": "2970", "alignment": 1, "markups": [], "type": 1}]}, "isFullContent": true}, "webCanonicalUrl": "", "notifyFacebook": false, "experimentalCss": "", "virtuals": {"links": {"entries": [], "generatedAt": 1481587559596, "version": "0.3"}, "imageCount": 0, "socialRecommendsCount": 0, "wordCount": 7, "totalClapCount": 0, "responsesCreatedCount": 0, "isLockedPreviewOnly": false, "usersBySocialRecommends": [], "isBookmarked": false, "recommends": 3, "subtitle": "", "takeoverId": "", "metaDescription": "", "previewImage": {"originalHeight": 0, "originalWidth": 0, "imageId": "", "height": 0, "filter": "", "width": 0, "strategy": "resample", "backgroundSize": ""}, "readingTime": 0.026415094339622643, "allowNotes": true, "tags": []}, "allowResponses": true, "homeCollectionId": "", "isSponsored": false, "importedUrl": "", "vote": false, "acceptedAt": 0, "firstPublishedAt": 1481587559142, "approvedHomeCollectionId": "", "type": "Post", "latestRev": 7, "content": {"postDisplay": {"coverless": true}}, "latestPublishedVersion": "d10f39a36f73", "hasUnpublishedEdits": false, "notifyTwitter": false, "isApprovedTranslation": false, "creatorId": "8804c3026cce", "visibility": 0, "translationSourcePostId": "", "latestPublishedAt": 1481587559142, "canonicalUrl": "", "coverless": true, "migrationId": "", "uniqueSlug": "of-course-glad-you-enjoyed-it-mitzi-c8cba35f08da", "latestVersion": "d10f39a36f73", "isSeries": false}, "67a15fd0d2d2": {"importedPublishedAt": 0, "inResponseToPostId": "c697f9fa0b27", "notifyFollowers": true, "seriesLastAppendedAt": 0, "translationSourceCreatorId": "", "displayAuthor": "", "isTitleSynthesized": true, "detectedLanguage": "un", "license": 0, "id": "67a15fd0d2d2", "createdAt": 1481587581595, "inResponseToRemovedAt": 0, "isRequestToPubDisabled": false, "responseHiddenOnParentPostAt": 0, "newsletterId": "", "title": "Thanks, Luis!", "slug": "thanks-luis", "versionId": "1fcaad1084fa", "inResponseToMediaResourceId": "d8acc612b38bdf75c352703b1420074c", "isSubscriptionLocked": false, "updatedAt": 1481587584221, "mediumUrl": "", "previewContent": {"bodyModel": {"sections": [{"startIndex": 0}], "paragraphs": [{"text": "Thanks, Luis!", "name": "0ac2", "alignment": 1, "markups": [], "type": 1}]}, "isFullContent": true}, "webCanonicalUrl": "", "notifyFacebook": false, "experimentalCss": "", "virtuals": {"links": {"entries": [], "generatedAt": 1481587584578, "version": "0.3"}, "imageCount": 0, "socialRecommendsCount": 0, "wordCount": 2, "totalClapCount": 0, "responsesCreatedCount": 0, "isLockedPreviewOnly": false, "usersBySocialRecommends": [], "isBookmarked": false, "recommends": 1, "subtitle": "", "takeoverId": "", "metaDescription": "", "previewImage": {"originalHeight": 0, "originalWidth": 0, "imageId": "", "height": 0, "filter": "", "width": 0, "strategy": "resample", "backgroundSize": ""}, "readingTime": 0.007547169811320755, "allowNotes": true, "tags": []}, "allowResponses": true, "homeCollectionId": "", "isSponsored": false, "importedUrl": "", "vote": false, "acceptedAt": 0, "firstPublishedAt": 1481587584221, "approvedHomeCollectionId": "", "type": "Post", "latestRev": 4, "content": {"postDisplay": {"coverless": true}}, "latestPublishedVersion": "1fcaad1084fa", "hasUnpublishedEdits": false, "notifyTwitter": false, "isApprovedTranslation": false, "creatorId": "8804c3026cce", "visibility": 0, "translationSourcePostId": "", "latestPublishedAt": 1481587584221, "canonicalUrl": "", "coverless": true, "migrationId": "", "uniqueSlug": "thanks-luis-67a15fd0d2d2", "latestVersion": "1fcaad1084fa", "isSeries": false}, "e9482caf67be": {"importedPublishedAt": 0, "inResponseToPostId": "6cb23738f823", "notifyFollowers": true, "seriesLastAppendedAt": 0, "translationSourceCreatorId": "", "displayAuthor": "", "isTitleSynthesized": true, "detectedLanguage": "en", "license": 0, "id": "e9482caf67be", "createdAt": 1481585334556, "inResponseToRemovedAt": 0, "isRequestToPubDisabled": false, "responseHiddenOnParentPostAt": 0, "newsletterId": "", "title": "Thank you.", "slug": "thank-you", "versionId": "a56185b34781", "inResponseToMediaResourceId": "3a040e50cca709732cc42071e7c43389", "isSubscriptionLocked": false, "updatedAt": 1481585397408, "mediumUrl": "", "previewContent": {"bodyModel": {"sections": [{"startIndex": 0}], "paragraphs": [{"text": "Thank you.", "name": "f8e7", "alignment": 1, "markups": [], "type": 1}, {"text": "I needed this.", "name": "f3b7", "alignment": 1, "markups": [], "type": 1}]}, "isFullContent": true}, "webCanonicalUrl": "", "notifyFacebook": false, "experimentalCss": "", "virtuals": {"links": {"entries": [], "generatedAt": 1481585397072, "version": "0.3"}, "imageCount": 0, "socialRecommendsCount": 0, "wordCount": 5, "totalClapCount": 0, "responsesCreatedCount": 1, "isLockedPreviewOnly": false, "usersBySocialRecommends": [], "isBookmarked": false, "recommends": 4, "subtitle": "I needed this.", "takeoverId": "", "metaDescription": "", "previewImage": {"originalHeight": 0, "originalWidth": 0, "imageId": "", "height": 0, "filter": "", "width": 0, "strategy": "resample", "backgroundSize": ""}, "readingTime": 0.018867924528301886, "allowNotes": true, "tags": [{"name": "Social Media", "slug": "social-media", "metadata": {"coverImage": {"id": "1*uOkczl-rzzPqbQTw6PSFYw.jpeg"}, "postCount": 74543, "followerCount": 1060354}, "postCount": 74543, "type": "Tag", "virtuals": {"isFollowing": false}}, {"name": "Brain Booster", "slug": "brain-booster", "metadata": {"coverImage": {"originalHeight": 3258, "originalWidth": 8333, "id": "1*2vXpMV-d_9GAremWdh8k2g.png"}, "postCount": 134, "followerCount": 20}, "postCount": 134, "type": "Tag", "virtuals": {"isFollowing": false}}, {"name": "Positivity", "slug": "positivity", "metadata": {"coverImage": {"originalHeight": 750, "originalWidth": 500, "id": "1*QW5v4Jf3EixoURjIc2Qw_A.jpeg"}, "postCount": 971, "followerCount": 73}, "postCount": 971, "type": "Tag", "virtuals": {"isFollowing": false}}]}, "allowResponses": true, "homeCollectionId": "", "isSponsored": false, "importedUrl": "", "vote": false, "acceptedAt": 0, "firstPublishedAt": 1481585396605, "approvedHomeCollectionId": "", "type": "Post", "latestRev": 12, "content": {"subtitle": "I needed this.", "postDisplay": {"coverless": true}}, "latestPublishedVersion": "a56185b34781", "hasUnpublishedEdits": false, "notifyTwitter": false, "isApprovedTranslation": false, "creatorId": "9e04cd18f6c8", "visibility": 0, "translationSourcePostId": "", "latestPublishedAt": 1481585396605, "canonicalUrl": "", "coverless": true, "migrationId": "", "uniqueSlug": "thank-you-e9482caf67be", "latestVersion": "a56185b34781", "isSeries": false}, "7436cd84936b": {"importedPublishedAt": 0, "inResponseToPostId": "6cb23738f823", "notifyFollowers": true, "seriesLastAppendedAt": 0, "translationSourceCreatorId": "", "displayAuthor": "", "isTitleSynthesized": true, "detectedLanguage": "en", "license": 0, "id": "7436cd84936b", "createdAt": 1481643573826, "inResponseToRemovedAt": 0, "isRequestToPubDisabled": false, "responseHiddenOnParentPostAt": 0, "newsletterId": "", "title": "Chad, this is simply spot on!", "slug": "chad-this-is-simply-spot-on", "versionId": "7138724b76f0", "inResponseToMediaResourceId": "3a040e50cca709732cc42071e7c43389", "isSubscriptionLocked": false, "updatedAt": 1481643635077, "mediumUrl": "", "previewContent": {"bodyModel": {"sections": [{"startIndex": 0}], "paragraphs": [{"text": "Chad, this is simply spot on! Thank you for putting pen to the many random thoughts I have been pondering in my own mind.", "name": "f104", "alignment": 1, "markups": [], "type": 1}]}, "isFullContent": true}, "webCanonicalUrl": "", "notifyFacebook": false, "experimentalCss": "", "virtuals": {"links": {"entries": [], "generatedAt": 1481643634577, "version": "0.3"}, "imageCount": 0, "socialRecommendsCount": 0, "wordCount": 24, "totalClapCount": 0, "responsesCreatedCount": 0, "isLockedPreviewOnly": false, "usersBySocialRecommends": [], "isBookmarked": false, "recommends": 1, "subtitle": "", "takeoverId": "", "metaDescription": "", "previewImage": {"originalHeight": 0, "originalWidth": 0, "imageId": "", "height": 0, "filter": "", "width": 0, "strategy": "resample", "backgroundSize": ""}, "readingTime": 0.09056603773584905, "allowNotes": true, "tags": []}, "allowResponses": true, "homeCollectionId": "", "isSponsored": false, "importedUrl": "", "vote": false, "acceptedAt": 0, "firstPublishedAt": 1481643634103, "approvedHomeCollectionId": "", "type": "Post", "latestRev": 14, "content": {"postDisplay": {"coverless": true}}, "latestPublishedVersion": "7138724b76f0", "hasUnpublishedEdits": false, "notifyTwitter": false, "isApprovedTranslation": false, "creatorId": "9b68e37be4c4", "visibility": 0, "translationSourcePostId": "", "latestPublishedAt": 1481643634103, "canonicalUrl": "", "coverless": true, "migrationId": "", "uniqueSlug": "chad-this-is-simply-spot-on-7436cd84936b", "latestVersion": "7138724b76f0", "isSeries": false}, "f294f1e6e51b": {"importedPublishedAt": 0, "inResponseToPostId": "6cb23738f823", "notifyFollowers": true, "seriesLastAppendedAt": 0, "translationSourceCreatorId": "", "displayAuthor": "", "isTitleSynthesized": true, "detectedLanguage": "en", "license": 0, "id": "f294f1e6e51b", "createdAt": 1481676893640, "inResponseToRemovedAt": 0, "isRequestToPubDisabled": false, "responseHiddenOnParentPostAt": 0, "newsletterId": "", "title": "My first comment on Medium!", "slug": "my-first-comment-on-medium", "versionId": "4ef83f23d01d", "inResponseToMediaResourceId": "3a040e50cca709732cc42071e7c43389", "isSubscriptionLocked": false, "updatedAt": 1481677489357, "mediumUrl": "", "previewContent": {"bodyModel": {"sections": [{"startIndex": 0}], "paragraphs": [{"text": "My first comment on Medium! I was beginning to wonder how all these statements connect until I hit upon our finale, \u201c Your life is a story that you get to consciously author.\u201d Then it all comes together.", "name": "700d", "alignment": 1, "markups": [], "type": 1}, {"text": "I agree about social media. That endless scrolling feature is an evil thing, haha. You will never hit the bottom of a page\u2026", "name": "95df", "alignment": 1, "markups": [], "type": 1}]}, "isFullContent": false}, "webCanonicalUrl": "", "notifyFacebook": false, "experimentalCss": "", "virtuals": {"links": {"entries": [], "generatedAt": 1481677488988, "version": "0.3"}, "imageCount": 0, "socialRecommendsCount": 0, "wordCount": 166, "totalClapCount": 0, "responsesCreatedCount": 2, "isLockedPreviewOnly": false, "usersBySocialRecommends": [], "isBookmarked": false, "recommends": 2, "subtitle": "I agree about social media. That endless scrolling feature is an evil thing, haha. You will never hit the bottom of a page when reading\u2026", "takeoverId": "", "metaDescription": "", "previewImage": {"originalHeight": 0, "originalWidth": 0, "imageId": "", "height": 0, "filter": "", "width": 0, "strategy": "resample", "backgroundSize": ""}, "readingTime": 0.6264150943396226, "allowNotes": true, "tags": []}, "allowResponses": true, "homeCollectionId": "", "isSponsored": false, "importedUrl": "", "vote": false, "acceptedAt": 0, "firstPublishedAt": 1481677488644, "approvedHomeCollectionId": "", "type": "Post", "latestRev": 125, "content": {"subtitle": "I agree about social media. That endless scrolling feature is an evil thing, haha. You will never hit the bottom of a page when reading\u2026", "postDisplay": {"coverless": true}}, "latestPublishedVersion": "4ef83f23d01d", "hasUnpublishedEdits": false, "notifyTwitter": false, "isApprovedTranslation": false, "creatorId": "1bdc591ece16", "visibility": 0, "translationSourcePostId": "", "latestPublishedAt": 1481677488644, "canonicalUrl": "", "coverless": true, "migrationId": "", "uniqueSlug": "my-first-comment-on-medium-f294f1e6e51b", "latestVersion": "4ef83f23d01d", "isSeries": false}, "59e8c79700b9": {"importedPublishedAt": 0, "inResponseToPostId": "6cb23738f823", "notifyFollowers": true, "seriesLastAppendedAt": 0, "translationSourceCreatorId": "", "displayAuthor": "", "isTitleSynthesized": true, "detectedLanguage": "en", "license": 0, "id": "59e8c79700b9", "createdAt": 1481650433434, "inResponseToRemovedAt": 0, "isRequestToPubDisabled": false, "responseHiddenOnParentPostAt": 0, "newsletterId": "", "title": "As a meditation and Qigong instructor I really relate to boosting the brain and relieving stress\u2026", "slug": "as-a-meditation-and-qigong-instructor-i-really-relate-to-boosting-the-brain-and-relieving-stress", "versionId": "4c872cf2add4", "inResponseToMediaResourceId": "3a040e50cca709732cc42071e7c43389", "isSubscriptionLocked": false, "updatedAt": 1481650925937, "mediumUrl": "", "previewContent": {"bodyModel": {"sections": [{"startIndex": 0}], "paragraphs": [{"text": "As a meditation and Qigong instructor I really relate to boosting the brain and relieving stress through those modalities.", "name": "85a8", "alignment": 1, "markups": [], "type": 1}, {"text": "My question is: if you don\u2019t get a negative comment or someone doesn\u2019t act confrontational with you you haven\u2019t been heard? Hmm, I am not sure about that. I think many \u201clurkers and trolls\u201d do that not\u2026", "name": "16c8", "alignment": 1, "markups": [], "type": 1}]}, "isFullContent": false}, "webCanonicalUrl": "", "notifyFacebook": false, "experimentalCss": "", "virtuals": {"links": {"entries": [], "generatedAt": 1481650925515, "version": "0.3"}, "imageCount": 0, "socialRecommendsCount": 0, "wordCount": 244, "totalClapCount": 0, "responsesCreatedCount": 0, "isLockedPreviewOnly": false, "usersBySocialRecommends": [], "isBookmarked": false, "recommends": 2, "subtitle": "My question is: if you don\u2019t get a negative comment or someone doesn\u2019t act confrontational with you you haven\u2019t been heard? Hmm, I am not\u2026", "takeoverId": "", "metaDescription": "", "previewImage": {"originalHeight": 0, "originalWidth": 0, "imageId": "", "height": 0, "filter": "", "width": 0, "strategy": "resample", "backgroundSize": ""}, "readingTime": 0.9207547169811321, "allowNotes": true, "tags": []}, "allowResponses": true, "homeCollectionId": "", "isSponsored": false, "importedUrl": "", "vote": false, "acceptedAt": 0, "firstPublishedAt": 1481650925128, "approvedHomeCollectionId": "", "type": "Post", "latestRev": 95, "content": {"subtitle": "My question is: if you don\u2019t get a negative comment or someone doesn\u2019t act confrontational with you you haven\u2019t been heard? Hmm, I am not\u2026", "postDisplay": {"coverless": true}}, "latestPublishedVersion": "4c872cf2add4", "hasUnpublishedEdits": false, "notifyTwitter": false, "isApprovedTranslation": false, "creatorId": "12c1710d9a51", "visibility": 0, "translationSourcePostId": "", "latestPublishedAt": 1481650925128, "canonicalUrl": "", "coverless": true, "migrationId": "", "uniqueSlug": "as-a-meditation-and-qigong-instructor-i-really-relate-to-boosting-the-brain-and-relieving-stress-59e8c79700b9", "latestVersion": "4c872cf2add4", "isSeries": false}, "6cb23738f823": {"importedPublishedAt": 0, "inResponseToPostId": "", "notifyFollowers": true, "seriesLastAppendedAt": 0, "translationSourceCreatorId": "", "displayAuthor": "", "isTitleSynthesized": true, "detectedLanguage": "en", "license": 0, "id": "6cb23738f823", "createdAt": 1481310307618, "inResponseToRemovedAt": 0, "isRequestToPubDisabled": false, "responseHiddenOnParentPostAt": 0, "newsletterId": "3227bfc40e07", "title": "Social media fasts, brain boosters, soundtracks that increase attention, and real friendships", "slug": "social-media-fasts-brain-boosters-soundtracks-that-increase-attention-and-real-friendships", "versionId": "9074948bf54e", "inResponseToMediaResourceId": "", "isSubscriptionLocked": false, "updatedAt": 1481644522808, "mediumUrl": "", "previewContent": {"bodyModel": {"sections": [{"startIndex": 0}], "paragraphs": [{"text": "Social media fasts, brain boosters, soundtracks that increase attention, and real friendships", "name": "ff63", "alignment": 1, "markups": [{"end": 93, "start": 0, "type": 1}], "type": 3}, {"name": "e7e0", "metadata": {"originalHeight": 1200, "originalWidth": 1600, "id": "0*0FeeeJGWp3n8ybP0."}, "text": "", "layout": 9, "markups": [], "type": 4}]}, "isFullContent": false}, "webCanonicalUrl": "", "notifyFacebook": false, "experimentalCss": "", "virtuals": {"links": {"entries": [{"alts": [{"url": "https://cdn.ampproject.org/c/mobile.nytimes.com/2016/11/20/jobs/quit-social-media-your-career-may-depend-on-it.amp.html", "type": 1}, {"url": "nytimes://reader/id/100000004756236", "type": 3}, {"url": "nytimes://www.nytimes.com/2016/11/20/jobs/quit-social-media-your-career-may-depend-on-it.html", "type": 2}], "url": "http://www.nytimes.com/2016/11/20/jobs/quit-social-media-your-career-may-depend-on-it.html"}, {"alts": [{"url": "medium://the-mission", "type": 2}, {"url": "medium://the-mission", "type": 3}], "url": "http://www.Medium.com/the-mission"}, {"alts": [{"url": "https://cdn.ampproject.org/c/www.telegraph.co.uk/science/2016/12/08/take-deep-breathinhaling-nose-stimulates-brain-boosts-memory/amp/", "type": 1}], "url": "http://www.telegraph.co.uk/science/2016/12/08/take-deep-breathinhaling-nose-stimulates-brain-boosts-memory/"}], "generatedAt": 1481644524249, "version": "0.3"}, "imageCount": 3, "tags": [{"name": "Life", "slug": "life", "metadata": {"coverImage": {"id": "1*0sJtn9WT-yfCMX8S8LyYVg.jpeg"}, "postCount": 136523, "followerCount": 957785}, "postCount": 136523, "type": "Tag", "virtuals": {"isFollowing": false}}, {"name": "Self Improvement", "slug": "self-improvement", "metadata": {"coverImage": {"id": "1*70mWmxgf52m1YqTcCfRkkQ.jpeg"}, "postCount": 64264, "followerCount": 1157395}, "postCount": 64264, "type": "Tag", "virtuals": {"isFollowing": false}}, {"name": "Life Lessons", "slug": "life-lessons", "metadata": {"coverImage": {"id": "1*xJV8uYsDYrnDwulfbMByRQ.jpeg"}, "postCount": 121964, "followerCount": 960501}, "postCount": 121964, "type": "Tag", "virtuals": {"isFollowing": false}}, {"name": "Personal Development", "slug": "personal-development", "metadata": {"coverImage": {"originalHeight": 2392, "originalWidth": 4287, "isFeatured": true, "id": "1*Sqb7pTtbgxeOgbgJDVGj7w.jpeg"}, "postCount": 21807, "followerCount": 11643}, "postCount": 21807, "type": "Tag", "virtuals": {"isFollowing": false}}, {"name": "Social Media", "slug": "social-media", "metadata": {"coverImage": {"id": "1*uOkczl-rzzPqbQTw6PSFYw.jpeg"}, "postCount": 74543, "followerCount": 1060354}, "postCount": 74543, "type": "Tag", "virtuals": {"isFollowing": false}}], "wordCount": 1140, "socialRecommendsCount": 0, "responsesCreatedCount": 25, "isLockedPreviewOnly": false, "usersBySocialRecommends": [], "isBookmarked": false, "publishedInCount": 1, "subtitle": "Should you fast from social media?", "takeoverId": "", "metaDescription": "", "previewImage": {"originalHeight": 1200, "originalWidth": 1600, "imageId": "0*0FeeeJGWp3n8ybP0.", "height": 0, "filter": "", "width": 0, "strategy": "resample", "backgroundSize": ""}, "totalClapCount": 0, "readingTime": 4.85188679245283, "recommends": 600, "statusForCollection": "APPROVED", "allowNotes": true}, "allowResponses": true, "homeCollectionId": "b230ea2a6eb8", "isSponsored": false, "importedUrl": "", "vote": false, "acceptedAt": 0, "firstPublishedAt": 1481580459581, "approvedHomeCollectionId": "b230ea2a6eb8", "type": "Post", "latestRev": 537, "content": {"subtitle": "Should you fast from social media?", "postDisplay": {"coverless": true}}, "latestPublishedVersion": "9074948bf54e", "hasUnpublishedEdits": false, "notifyTwitter": false, "isApprovedTranslation": false, "creatorId": "8804c3026cce", "visibility": 0, "translationSourcePostId": "", "latestPublishedAt": 1481644522808, "canonicalUrl": "", "coverless": true, "migrationId": "", "uniqueSlug": "social-media-fasts-brain-boosters-soundtracks-that-increase-attention-and-real-friendships-6cb23738f823", "latestVersion": "9074948bf54e", "isSeries": false}, "81f61f80e512": {"importedPublishedAt": 0, "inResponseToPostId": "6cb23738f823", "notifyFollowers": true, "seriesLastAppendedAt": 0, "translationSourceCreatorId": "", "displayAuthor": "", "isTitleSynthesized": true, "detectedLanguage": "en", "license": 0, "id": "81f61f80e512", "createdAt": 1481706454323, "inResponseToRemovedAt": 0, "isRequestToPubDisabled": false, "responseHiddenOnParentPostAt": 0, "newsletterId": "", "title": "Thanks for this Article Chad!", "slug": "thanks-for-this-article-chad", "versionId": "21e3142845d", "inResponseToMediaResourceId": "3a040e50cca709732cc42071e7c43389", "isSubscriptionLocked": false, "updatedAt": 1481707959815, "mediumUrl": "", "previewContent": {"bodyModel": {"sections": [{"startIndex": 0}], "paragraphs": [{"text": "Thanks for this Article Chad! The point that Medium is not a regular social network got me thinking. A while ago I joined Facebook to stay in contact with old friends and acquaintances, but now it\u2019s all about liking and sharing random stuff. Opposed to Medium, there is very little original content.", "name": "e849", "alignment": 1, "markups": [], "type": 1}]}, "isFullContent": false}, "webCanonicalUrl": "", "notifyFacebook": false, "experimentalCss": "", "virtuals": {"links": {"entries": [], "generatedAt": 1481707959686, "version": "0.3"}, "imageCount": 0, "socialRecommendsCount": 0, "wordCount": 90, "totalClapCount": 0, "responsesCreatedCount": 0, "isLockedPreviewOnly": false, "usersBySocialRecommends": [], "isBookmarked": false, "recommends": 1, "subtitle": "On using music for focus: I tried focus at will some time ago\u200a- https://www.focusatwill.com\u00a0. I\u2019m not sure if it\u2019s really due to their\u2026", "takeoverId": "", "metaDescription": "", "previewImage": {"originalHeight": 0, "originalWidth": 0, "imageId": "", "height": 0, "filter": "", "width": 0, "strategy": "resample", "backgroundSize": ""}, "readingTime": 0.33962264150943394, "allowNotes": true, "tags": [{"name": "Social Media", "slug": "social-media", "metadata": {"coverImage": {"id": "1*uOkczl-rzzPqbQTw6PSFYw.jpeg"}, "postCount": 74543, "followerCount": 1060354}, "postCount": 74543, "type": "Tag", "virtuals": {"isFollowing": false}}, {"name": "Facebook", "slug": "facebook", "metadata": {"coverImage": {"originalHeight": 1024, "originalWidth": 1536, "focusPercentY": 42, "isFeatured": true, "id": "1*Vg_sHxqswN3Fa1c_PtEnSA.jpeg", "focusPercentX": 56}, "postCount": 26136, "followerCount": 2711}, "postCount": 26136, "type": "Tag", "virtuals": {"isFollowing": false}}, {"name": "Focus", "slug": "focus", "metadata": {"coverImage": {"originalHeight": 960, "originalWidth": 1280, "id": "1*8biWkULAy6ijPARD0pYgeA.jpeg"}, "postCount": 1775, "followerCount": 166}, "postCount": 1775, "type": "Tag", "virtuals": {"isFollowing": false}}]}, "allowResponses": true, "homeCollectionId": "", "isSponsored": false, "importedUrl": "", "vote": false, "acceptedAt": 0, "firstPublishedAt": 1481707959019, "approvedHomeCollectionId": "", "type": "Post", "latestRev": 66, "content": {"subtitle": "On using music for focus: I tried focus at will some time ago\u200a- https://www.focusatwill.com\u00a0. I\u2019m not sure if it\u2019s really due to their\u2026", "postDisplay": {"coverless": true}}, "latestPublishedVersion": "21e3142845d", "hasUnpublishedEdits": false, "notifyTwitter": false, "isApprovedTranslation": false, "creatorId": "66ffd0314a1a", "visibility": 0, "translationSourcePostId": "", "latestPublishedAt": 1481707959019, "canonicalUrl": "", "coverless": true, "migrationId": "", "uniqueSlug": "thanks-for-this-article-chad-81f61f80e512", "latestVersion": "21e3142845d", "isSeries": false}, "b47aa27ced51": {"importedPublishedAt": 0, "inResponseToPostId": "6cb23738f823", "notifyFollowers": true, "seriesLastAppendedAt": 0, "translationSourceCreatorId": "", "displayAuthor": "", "isTitleSynthesized": true, "detectedLanguage": "en", "license": 0, "id": "b47aa27ced51", "createdAt": 1482101978505, "inResponseToRemovedAt": 0, "isRequestToPubDisabled": false, "responseHiddenOnParentPostAt": 0, "newsletterId": "", "title": "I\u2019m quite new to medium and really becoming fascinated by the quality of information that is\u2026", "slug": "im-quite-new-to-medium-and-really-becoming-fascinated-by-the-quality-of-information-that-is", "versionId": "bd1e63f6f8b", "inResponseToMediaResourceId": "3a040e50cca709732cc42071e7c43389", "isSubscriptionLocked": false, "updatedAt": 1482102122770, "mediumUrl": "", "previewContent": {"bodyModel": {"sections": [{"startIndex": 0}], "paragraphs": [{"text": "I\u2019m quite new to medium and really becoming fascinated by the quality of information that is created. Chad\u200a\u2014\u200athis is fantastic guidance and so eloquently written. Thoroughly enjoyed.", "name": "ae76", "alignment": 1, "markups": [], "type": 1}]}, "isFullContent": true}, "webCanonicalUrl": "", "notifyFacebook": false, "experimentalCss": "", "virtuals": {"links": {"entries": [], "generatedAt": 1482102122310, "version": "0.3"}, "imageCount": 0, "socialRecommendsCount": 0, "wordCount": 29, "totalClapCount": 0, "responsesCreatedCount": 0, "isLockedPreviewOnly": false, "usersBySocialRecommends": [], "isBookmarked": false, "recommends": 1, "subtitle": "", "takeoverId": "", "metaDescription": "", "previewImage": {"originalHeight": 0, "originalWidth": 0, "imageId": "", "height": 0, "filter": "", "width": 0, "strategy": "resample", "backgroundSize": ""}, "readingTime": 0.10943396226415095, "allowNotes": true, "tags": []}, "allowResponses": true, "homeCollectionId": "", "isSponsored": false, "importedUrl": "", "vote": false, "acceptedAt": 0, "firstPublishedAt": 1482102121896, "approvedHomeCollectionId": "", "type": "Post", "latestRev": 13, "content": {"postDisplay": {"coverless": true}}, "latestPublishedVersion": "bd1e63f6f8b", "hasUnpublishedEdits": false, "notifyTwitter": false, "isApprovedTranslation": false, "creatorId": "28573f014ba4", "visibility": 0, "translationSourcePostId": "", "latestPublishedAt": 1482102121896, "canonicalUrl": "", "coverless": true, "migrationId": "", "uniqueSlug": "im-quite-new-to-medium-and-really-becoming-fascinated-by-the-quality-of-information-that-is-b47aa27ced51", "latestVersion": "bd1e63f6f8b", "isSeries": false}, "46834d8d6e2c": {"importedPublishedAt": 0, "inResponseToPostId": "44f7ae1d0822", "notifyFollowers": true, "seriesLastAppendedAt": 0, "translationSourceCreatorId": "", "displayAuthor": "", "isTitleSynthesized": true, "detectedLanguage": "en", "license": 0, "id": "46834d8d6e2c", "createdAt": 1481592747684, "inResponseToRemovedAt": 0, "isRequestToPubDisabled": false, "responseHiddenOnParentPostAt": 0, "newsletterId": "", "title": "Thanks, Isabell! Of course, and glad you enjoyed it.", "slug": "thanks-isabell-of-course-and-glad-you-enjoyed-it", "versionId": "8f0fe4b58634", "inResponseToMediaResourceId": "990fdae09f173af24740563e9c6f58dc", "isSubscriptionLocked": false, "updatedAt": 1481592784427, "mediumUrl": "", "previewContent": {"bodyModel": {"sections": [{"startIndex": 0}], "paragraphs": [{"text": "Thanks, Isabell! Of course, and glad you enjoyed it.", "name": "b219", "alignment": 1, "markups": [], "type": 1}, {"text": "\u201cYou have no business cruising on social media if your business is creating a solution to a world problem.\u201d", "name": "b6aa", "alignment": 1, "markups": [], "type": 1}, {"text": "Well said! :)", "name": "e130", "alignment": 1, "markups": [], "type": 1}]}, "isFullContent": true}, "webCanonicalUrl": "", "notifyFacebook": false, "experimentalCss": "", "virtuals": {"links": {"entries": [], "generatedAt": 1481592784206, "version": "0.3"}, "imageCount": 0, "socialRecommendsCount": 0, "wordCount": 31, "totalClapCount": 0, "responsesCreatedCount": 0, "isLockedPreviewOnly": false, "usersBySocialRecommends": [], "isBookmarked": false, "recommends": 2, "subtitle": "\u201cYou have no business cruising on social media if your business is creating a solution to a world problem.\u201d", "takeoverId": "", "metaDescription": "", "previewImage": {"originalHeight": 0, "originalWidth": 0, "imageId": "", "height": 0, "filter": "", "width": 0, "strategy": "resample", "backgroundSize": ""}, "readingTime": 0.1169811320754717, "allowNotes": true, "tags": []}, "allowResponses": true, "homeCollectionId": "", "isSponsored": false, "importedUrl": "", "vote": false, "acceptedAt": 0, "firstPublishedAt": 1481592783797, "approvedHomeCollectionId": "", "type": "Post", "latestRev": 19, "content": {"subtitle": "\u201cYou have no business cruising on social media if your business is creating a solution to a world problem.\u201d", "postDisplay": {"coverless": true}}, "latestPublishedVersion": "8f0fe4b58634", "hasUnpublishedEdits": false, "notifyTwitter": false, "isApprovedTranslation": false, "creatorId": "8804c3026cce", "visibility": 0, "translationSourcePostId": "", "latestPublishedAt": 1481592783797, "canonicalUrl": "", "coverless": true, "migrationId": "", "uniqueSlug": "thanks-isabell-of-course-and-glad-you-enjoyed-it-46834d8d6e2c", "latestVersion": "8f0fe4b58634", "isSeries": false}, "ee986bfd78e0": {"importedPublishedAt": 0, "inResponseToPostId": "6cb23738f823", "notifyFollowers": true, "seriesLastAppendedAt": 0, "translationSourceCreatorId": "", "displayAuthor": "", "isTitleSynthesized": true, "detectedLanguage": "un", "license": 0, "id": "ee986bfd78e0", "createdAt": 1481605369151, "inResponseToRemovedAt": 0, "isRequestToPubDisabled": false, "responseHiddenOnParentPostAt": 0, "newsletterId": "", "title": "It\u2019s good", "slug": "its-good", "versionId": "e541ff551449", "inResponseToMediaResourceId": "3a040e50cca709732cc42071e7c43389", "isSubscriptionLocked": false, "updatedAt": 1481605372723, "mediumUrl": "", "previewContent": {"bodyModel": {"sections": [{"startIndex": 0}], "paragraphs": [{"text": "It\u2019s good", "name": "8c10", "alignment": 1, "markups": [], "type": 1}]}, "isFullContent": true}, "webCanonicalUrl": "", "notifyFacebook": false, "experimentalCss": "", "virtuals": {"links": {"entries": [], "generatedAt": 1481605373045, "version": "0.3"}, "imageCount": 0, "socialRecommendsCount": 0, "wordCount": 2, "totalClapCount": 0, "responsesCreatedCount": 0, "isLockedPreviewOnly": false, "usersBySocialRecommends": [], "isBookmarked": false, "recommends": 0, "subtitle": "", "takeoverId": "", "metaDescription": "", "previewImage": {"originalHeight": 0, "originalWidth": 0, "imageId": "", "height": 0, "filter": "", "width": 0, "strategy": "resample", "backgroundSize": ""}, "readingTime": 0.007547169811320755, "allowNotes": true, "tags": []}, "allowResponses": true, "homeCollectionId": "", "isSponsored": false, "importedUrl": "", "vote": false, "acceptedAt": 0, "firstPublishedAt": 1481605372723, "approvedHomeCollectionId": "", "type": "Post", "latestRev": 4, "content": {"postDisplay": {"coverless": true}}, "latestPublishedVersion": "e541ff551449", "hasUnpublishedEdits": false, "notifyTwitter": false, "isApprovedTranslation": false, "creatorId": "f269f860c9cc", "visibility": 0, "translationSourcePostId": "", "latestPublishedAt": 1481605372723, "canonicalUrl": "", "coverless": true, "migrationId": "", "uniqueSlug": "its-good-ee986bfd78e0", "latestVersion": "e541ff551449", "isSeries": false}, "92594c93d960": {"importedPublishedAt": 0, "inResponseToPostId": "6cb23738f823", "notifyFollowers": true, "seriesLastAppendedAt": 0, "translationSourceCreatorId": "", "displayAuthor": "", "isTitleSynthesized": true, "detectedLanguage": "en", "license": 0, "id": "92594c93d960", "createdAt": 1482201709104, "inResponseToRemovedAt": 0, "isRequestToPubDisabled": false, "responseHiddenOnParentPostAt": 0, "newsletterId": "", "title": "One of the many reasons why I love Medium, by the way.", "slug": "one-of-the-many-reasons-why-i-love-medium-by-the-way", "versionId": "21896068d523", "inResponseToMediaResourceId": "f03c0ad0e37a47b675da6ce41f07a38a", "isSubscriptionLocked": false, "updatedAt": 1482201743309, "mediumUrl": "", "previewContent": {"bodyModel": {"sections": [{"startIndex": 0}], "paragraphs": [{"text": "One of the many reasons why I love Medium, by the way.", "name": "fa15", "alignment": 1, "markups": [], "type": 1}]}, "isFullContent": true}, "webCanonicalUrl": "", "notifyFacebook": false, "experimentalCss": "", "virtuals": {"links": {"entries": [], "generatedAt": 1482201743112, "version": "0.3"}, "imageCount": 0, "socialRecommendsCount": 0, "wordCount": 12, "totalClapCount": 0, "responsesCreatedCount": 0, "isLockedPreviewOnly": false, "usersBySocialRecommends": [], "isBookmarked": false, "recommends": 1, "subtitle": "", "takeoverId": "", "metaDescription": "", "previewImage": {"originalHeight": 0, "originalWidth": 0, "imageId": "", "height": 0, "filter": "", "width": 0, "strategy": "resample", "backgroundSize": ""}, "readingTime": 0.045283018867924525, "allowNotes": true, "tags": []}, "allowResponses": true, "homeCollectionId": "", "isSponsored": false, "importedUrl": "", "vote": false, "acceptedAt": 0, "firstPublishedAt": 1482201742664, "approvedHomeCollectionId": "", "type": "Post", "latestRev": 6, "content": {"postDisplay": {"coverless": true}}, "latestPublishedVersion": "21896068d523", "hasUnpublishedEdits": false, "notifyTwitter": false, "isApprovedTranslation": false, "creatorId": "f42556cd052b", "visibility": 0, "translationSourcePostId": "", "latestPublishedAt": 1482201742664, "canonicalUrl": "", "coverless": true, "migrationId": "", "uniqueSlug": "one-of-the-many-reasons-why-i-love-medium-by-the-way-92594c93d960", "latestVersion": "21896068d523", "isSeries": false}, "433822f756d": {"importedPublishedAt": 0, "inResponseToPostId": "6cb23738f823", "notifyFollowers": true, "seriesLastAppendedAt": 0, "translationSourceCreatorId": "", "displayAuthor": "", "isTitleSynthesized": true, "detectedLanguage": "en", "license": 0, "id": "433822f756d", "createdAt": 1481723385417, "inResponseToRemovedAt": 0, "isRequestToPubDisabled": false, "responseHiddenOnParentPostAt": 0, "newsletterId": "", "title": "Thanks for the reaffirmation.", "slug": "thanks-for-the-reaffirmation", "versionId": "e86b5310ef41", "inResponseToMediaResourceId": "3a040e50cca709732cc42071e7c43389", "isSubscriptionLocked": false, "updatedAt": 1481723501676, "mediumUrl": "", "previewContent": {"bodyModel": {"sections": [{"startIndex": 0}], "paragraphs": [{"text": "Thanks for the reaffirmation. The cool thing about the internet is that it is a giant room full of mirrors. It\u2019s also it failing. \u201cThere are two basic motivating forces: fear and love. When we are afraid, we pull back from life. When we are in love, we open to all that life has to offer with passion, excitement, and acceptance. We need to learn to\u2026", "name": "8e24", "alignment": 1, "markups": [], "type": 1}]}, "isFullContent": false}, "webCanonicalUrl": "", "notifyFacebook": false, "experimentalCss": "", "virtuals": {"links": {"entries": [], "generatedAt": 1481723501300, "version": "0.3"}, "imageCount": 0, "socialRecommendsCount": 0, "wordCount": 120, "totalClapCount": 0, "responsesCreatedCount": 0, "isLockedPreviewOnly": false, "usersBySocialRecommends": [], "isBookmarked": false, "recommends": 1, "subtitle": "\u2015 John Lennon", "takeoverId": "", "metaDescription": "", "previewImage": {"originalHeight": 0, "originalWidth": 0, "imageId": "", "height": 0, "filter": "", "width": 0, "strategy": "resample", "backgroundSize": ""}, "readingTime": 0.4528301886792453, "allowNotes": true, "tags": []}, "allowResponses": true, "homeCollectionId": "", "isSponsored": false, "importedUrl": "", "vote": false, "acceptedAt": 0, "firstPublishedAt": 1481723500751, "approvedHomeCollectionId": "", "type": "Post", "latestRev": 16, "content": {"subtitle": "\u2015 John Lennon", "postDisplay": {"coverless": true}}, "latestPublishedVersion": "e86b5310ef41", "hasUnpublishedEdits": false, "notifyTwitter": false, "isApprovedTranslation": false, "creatorId": "e71d494d8acc", "visibility": 0, "translationSourcePostId": "", "latestPublishedAt": 1481723500751, "canonicalUrl": "", "coverless": true, "migrationId": "", "uniqueSlug": "thanks-for-the-reaffirmation-433822f756d", "latestVersion": "e86b5310ef41", "isSeries": false}, "eb8311aeb9e6": {"importedPublishedAt": 0, "inResponseToPostId": "6cb23738f823", "notifyFollowers": true, "seriesLastAppendedAt": 0, "translationSourceCreatorId": "", "displayAuthor": "", "isTitleSynthesized": true, "detectedLanguage": "en", "license": 0, "id": "eb8311aeb9e6", "createdAt": 1483117780304, "inResponseToRemovedAt": 0, "isRequestToPubDisabled": false, "responseHiddenOnParentPostAt": 0, "newsletterId": "", "title": "Hey Chad, thanks for this.", "slug": "hey-chad-thanks-for-this", "versionId": "915ff1834314", "inResponseToMediaResourceId": "3a040e50cca709732cc42071e7c43389", "isSubscriptionLocked": false, "updatedAt": 1483118130111, "mediumUrl": "", "previewContent": {"bodyModel": {"sections": [{"startIndex": 0}], "paragraphs": [{"text": "Hey Chad, thanks for this. As a freelancer chaos can reign and sometimes it\u2019s tough to find calmness and focus in it all. This playlist has been killer for me. It\u2019s called the \u201cmost relaxing songs in the world\u201d and they have been scientifically studied to focus and calm the mind: https://open.spotify.com/user/1286544262@/playlist/31lxxIDyC3qYrtH6TpGFwx", "name": "bc2c", "alignment": 1, "markups": [], "type": 1}, {"text": "Zach", "name": "7f7a", "alignment": 1, "markups": [], "type": 1}]}, "isFullContent": true}, "webCanonicalUrl": "", "notifyFacebook": false, "experimentalCss": "", "virtuals": {"links": {"entries": [], "generatedAt": 1483118130395, "version": "0.3"}, "imageCount": 0, "socialRecommendsCount": 0, "wordCount": 53, "totalClapCount": 0, "responsesCreatedCount": 0, "isLockedPreviewOnly": false, "usersBySocialRecommends": [], "isBookmarked": false, "recommends": 0, "subtitle": "Zach", "takeoverId": "", "metaDescription": "", "previewImage": {"originalHeight": 0, "originalWidth": 0, "imageId": "", "height": 0, "filter": "", "width": 0, "strategy": "resample", "backgroundSize": ""}, "readingTime": 0.2, "allowNotes": true, "tags": [{"name": "Music", "slug": "music", "metadata": {"coverImage": {"id": "1*IiNmmcwgPtVI77r3VcrGjA.jpeg"}, "postCount": 68386, "followerCount": 626551}, "postCount": 68386, "type": "Tag", "virtuals": {"isFollowing": false}}, {"name": "Mindfulness", "slug": "mindfulness", "metadata": {"coverImage": {"originalHeight": 1944, "originalWidth": 1560, "id": "1*bRaqhvB1QexjQAju81Ry4g.jpeg"}, "postCount": 13406, "followerCount": 3756}, "postCount": 13406, "type": "Tag", "virtuals": {"isFollowing": false}}]}, "allowResponses": true, "homeCollectionId": "", "isSponsored": false, "importedUrl": "", "vote": false, "acceptedAt": 0, "firstPublishedAt": 1483117914303, "approvedHomeCollectionId": "", "type": "Post", "latestRev": 54, "content": {"subtitle": "Zach", "postDisplay": {"coverless": true}}, "latestPublishedVersion": "915ff1834314", "hasUnpublishedEdits": false, "notifyTwitter": false, "isApprovedTranslation": false, "creatorId": "9acc337a2cf5", "visibility": 0, "translationSourcePostId": "", "latestPublishedAt": 1483118130111, "canonicalUrl": "", "coverless": true, "migrationId": "", "uniqueSlug": "hey-chad-thanks-for-this-eb8311aeb9e6", "latestVersion": "915ff1834314", "isSeries": false}, "a38c34a21857": {"importedPublishedAt": 0, "inResponseToPostId": "6cb23738f823", "notifyFollowers": true, "seriesLastAppendedAt": 0, "translationSourceCreatorId": "", "displayAuthor": "", "isTitleSynthesized": true, "detectedLanguage": "en", "license": 0, "id": "a38c34a21857", "createdAt": 1481646830666, "inResponseToRemovedAt": 0, "isRequestToPubDisabled": false, "responseHiddenOnParentPostAt": 0, "newsletterId": "", "title": "Loved this one thank you!", "slug": "loved-this-one-thank-you", "versionId": "1623230e2559", "inResponseToMediaResourceId": "3a040e50cca709732cc42071e7c43389", "isSubscriptionLocked": false, "updatedAt": 1481646837671, "mediumUrl": "", "previewContent": {"bodyModel": {"sections": [{"startIndex": 0}], "paragraphs": [{"text": "Loved this one thank you!", "name": "ba00", "alignment": 1, "markups": [], "type": 1}]}, "isFullContent": true}, "webCanonicalUrl": "", "notifyFacebook": false, "experimentalCss": "", "virtuals": {"links": {"entries": [], "generatedAt": 1481646837284, "version": "0.3"}, "imageCount": 0, "socialRecommendsCount": 0, "wordCount": 5, "totalClapCount": 0, "responsesCreatedCount": 0, "isLockedPreviewOnly": false, "usersBySocialRecommends": [], "isBookmarked": false, "recommends": 1, "subtitle": "", "takeoverId": "", "metaDescription": "", "previewImage": {"originalHeight": 0, "originalWidth": 0, "imageId": "", "height": 0, "filter": "", "width": 0, "strategy": "resample", "backgroundSize": ""}, "readingTime": 0.018867924528301886, "allowNotes": true, "tags": []}, "allowResponses": true, "homeCollectionId": "", "isSponsored": false, "importedUrl": "", "vote": false, "acceptedAt": 0, "firstPublishedAt": 1481646836962, "approvedHomeCollectionId": "", "type": "Post", "latestRev": 6, "content": {"postDisplay": {"coverless": true}}, "latestPublishedVersion": "1623230e2559", "hasUnpublishedEdits": false, "notifyTwitter": false, "isApprovedTranslation": false, "creatorId": "b1f6b1234385", "visibility": 0, "translationSourcePostId": "", "latestPublishedAt": 1481646836962, "canonicalUrl": "", "coverless": true, "migrationId": "", "uniqueSlug": "loved-this-one-thank-you-a38c34a21857", "latestVersion": "1623230e2559", "isSeries": false}, "9f212d2f109c": {"importedPublishedAt": 0, "inResponseToPostId": "6cb23738f823", "notifyFollowers": true, "seriesLastAppendedAt": 0, "translationSourceCreatorId": "", "displayAuthor": "", "isTitleSynthesized": true, "detectedLanguage": "en", "license": 0, "id": "9f212d2f109c", "createdAt": 1481627074524, "inResponseToRemovedAt": 0, "isRequestToPubDisabled": false, "responseHiddenOnParentPostAt": 0, "newsletterId": "", "title": "Your life is a story that you get to consciously author.", "slug": "your-life-is-a-story-that-you-get-to-consciously-author", "versionId": "29be132b4b34", "inResponseToMediaResourceId": "3a040e50cca709732cc42071e7c43389", "isSubscriptionLocked": false, "updatedAt": 1481627083288, "mediumUrl": "", "previewContent": {"bodyModel": {"sections": [{"startIndex": 0}], "paragraphs": [{"text": "Your life is a story that you get to consciously author.", "name": "e6d2", "alignment": 1, "markups": [], "type": 1}, {"text": "Brilliantly put Chad\u00a0\u263a", "name": "cfa5", "alignment": 1, "markups": [], "type": 1}]}, "isFullContent": true}, "webCanonicalUrl": "", "notifyFacebook": false, "experimentalCss": "", "virtuals": {"links": {"entries": [], "generatedAt": 1481627082932, "version": "0.3"}, "imageCount": 0, "socialRecommendsCount": 0, "wordCount": 15, "totalClapCount": 0, "responsesCreatedCount": 0, "isLockedPreviewOnly": false, "usersBySocialRecommends": [], "isBookmarked": false, "recommends": 1, "subtitle": "Brilliantly put Chad\u00a0\u263a", "takeoverId": "", "metaDescription": "", "previewImage": {"originalHeight": 0, "originalWidth": 0, "imageId": "", "height": 0, "filter": "", "width": 0, "strategy": "resample", "backgroundSize": ""}, "readingTime": 0.05660377358490566, "allowNotes": true, "tags": []}, "allowResponses": true, "homeCollectionId": "", "isSponsored": false, "importedUrl": "", "vote": false, "acceptedAt": 0, "firstPublishedAt": 1481627082597, "approvedHomeCollectionId": "", "type": "Post", "latestRev": 5, "content": {"subtitle": "Brilliantly put Chad\u00a0\u263a", "postDisplay": {"coverless": true}}, "latestPublishedVersion": "29be132b4b34", "hasUnpublishedEdits": false, "notifyTwitter": false, "isApprovedTranslation": false, "creatorId": "74c2db95497c", "visibility": 0, "translationSourcePostId": "", "latestPublishedAt": 1481627082597, "canonicalUrl": "", "coverless": true, "migrationId": "", "uniqueSlug": "your-life-is-a-story-that-you-get-to-consciously-author-9f212d2f109c", "latestVersion": "29be132b4b34", "isSeries": false}, "50e37e144fe3": {"importedPublishedAt": 0, "inResponseToPostId": "6cb23738f823", "notifyFollowers": true, "seriesLastAppendedAt": 0, "translationSourceCreatorId": "", "displayAuthor": "", "isTitleSynthesized": true, "detectedLanguage": "en", "license": 0, "id": "50e37e144fe3", "createdAt": 1481613609739, "inResponseToRemovedAt": 0, "isRequestToPubDisabled": false, "responseHiddenOnParentPostAt": 0, "newsletterId": "", "title": "Better to breathe in for 3 seconds and out for five ( reverse as you say)", "slug": "better-to-breathe-in-for-3-seconds-and-out-for-five-reverse-as-you-say", "versionId": "5e9d7aacdac9", "inResponseToMediaResourceId": "3a040e50cca709732cc42071e7c43389", "isSubscriptionLocked": false, "updatedAt": 1481613682094, "mediumUrl": "", "previewContent": {"bodyModel": {"sections": [{"startIndex": 0}], "paragraphs": [{"text": "Better to breathe in for 3 seconds and out for five ( reverse as you say)", "name": "bc40", "alignment": 1, "markups": [], "type": 1}]}, "isFullContent": true}, "webCanonicalUrl": "", "notifyFacebook": false, "experimentalCss": "", "virtuals": {"links": {"entries": [], "generatedAt": 1481613681577, "version": "0.3"}, "imageCount": 0, "socialRecommendsCount": 0, "wordCount": 16, "totalClapCount": 0, "responsesCreatedCount": 0, "isLockedPreviewOnly": false, "usersBySocialRecommends": [], "isBookmarked": false, "recommends": 1, "subtitle": "", "takeoverId": "", "metaDescription": "", "previewImage": {"originalHeight": 0, "originalWidth": 0, "imageId": "", "height": 0, "filter": "", "width": 0, "strategy": "resample", "backgroundSize": ""}, "readingTime": 0.06037735849056604, "allowNotes": true, "tags": []}, "allowResponses": true, "homeCollectionId": "", "isSponsored": false, "importedUrl": "", "vote": false, "acceptedAt": 0, "firstPublishedAt": 1481613681165, "approvedHomeCollectionId": "", "type": "Post", "latestRev": 14, "content": {"postDisplay": {"coverless": true}}, "latestPublishedVersion": "5e9d7aacdac9", "hasUnpublishedEdits": false, "notifyTwitter": false, "isApprovedTranslation": false, "creatorId": "28cf1c3158a8", "visibility": 0, "translationSourcePostId": "", "latestPublishedAt": 1481613681165, "canonicalUrl": "", "coverless": true, "migrationId": "", "uniqueSlug": "better-to-breathe-in-for-3-seconds-and-out-for-five-reverse-as-you-say-50e37e144fe3", "latestVersion": "5e9d7aacdac9", "isSeries": false}, "44f7ae1d0822": {"importedPublishedAt": 0, "inResponseToPostId": "6cb23738f823", "notifyFollowers": true, "seriesLastAppendedAt": 0, "translationSourceCreatorId": "", "displayAuthor": "", "isTitleSynthesized": true, "detectedLanguage": "en", "license": 0, "id": "44f7ae1d0822", "createdAt": 1481588981134, "inResponseToRemovedAt": 0, "isRequestToPubDisabled": false, "responseHiddenOnParentPostAt": 0, "newsletterId": "", "title": "Took the words right out of my mouth.", "slug": "took-the-words-right-out-of-my-mouth", "versionId": "9fa60ae286e", "inResponseToMediaResourceId": "3a040e50cca709732cc42071e7c43389", "isSubscriptionLocked": false, "updatedAt": 1481589535037, "mediumUrl": "", "previewContent": {"bodyModel": {"sections": [{"startIndex": 0}], "paragraphs": [{"text": "Took the words right out of my mouth. Thank you for sharing such an important message. I was just have the conversation literally 5 minute ago with a friend, that my rule is that I don\u2019t spend any longer than 5 minutes in the morning and at night on Facebook/Twitter/Instagram.", "name": "5d6b", "alignment": 1, "markups": [], "type": 1}]}, "isFullContent": false}, "webCanonicalUrl": "", "notifyFacebook": false, "experimentalCss": "", "virtuals": {"links": {"entries": [], "generatedAt": 1481589534701, "version": "0.3"}, "imageCount": 0, "socialRecommendsCount": 0, "wordCount": 124, "totalClapCount": 0, "responsesCreatedCount": 1, "isLockedPreviewOnly": false, "usersBySocialRecommends": [], "isBookmarked": false, "recommends": 4, "subtitle": "The quote from Cal Newport makes a powerful distinction when he stated, \u201ca service designed to fragment my attention is as scary to me as\u2026", "takeoverId": "", "metaDescription": "", "previewImage": {"originalHeight": 0, "originalWidth": 0, "imageId": "", "height": 0, "filter": "", "width": 0, "strategy": "resample", "backgroundSize": ""}, "readingTime": 0.4679245283018868, "allowNotes": true, "tags": []}, "allowResponses": true, "homeCollectionId": "", "isSponsored": false, "importedUrl": "", "vote": false, "acceptedAt": 0, "firstPublishedAt": 1481589534372, "approvedHomeCollectionId": "", "type": "Post", "latestRev": 89, "content": {"subtitle": "The quote from Cal Newport makes a powerful distinction when he stated, \u201ca service designed to fragment my attention is as scary to me as\u2026", "postDisplay": {"coverless": true}}, "latestPublishedVersion": "9fa60ae286e", "hasUnpublishedEdits": false, "notifyTwitter": false, "isApprovedTranslation": false, "creatorId": "ab0d3aa95c74", "visibility": 0, "translationSourcePostId": "", "latestPublishedAt": 1481589534372, "canonicalUrl": "", "coverless": true, "migrationId": "", "uniqueSlug": "took-the-words-right-out-of-my-mouth-44f7ae1d0822", "latestVersion": "9fa60ae286e", "isSeries": false}, "8303fae9980c": {"importedPublishedAt": 0, "inResponseToPostId": "6cb23738f823", "notifyFollowers": true, "seriesLastAppendedAt": 0, "translationSourceCreatorId": "", "displayAuthor": "", "isTitleSynthesized": true, "detectedLanguage": "en", "license": 0, "id": "8303fae9980c", "createdAt": 1481602149593, "inResponseToRemovedAt": 0, "isRequestToPubDisabled": false, "responseHiddenOnParentPostAt": 0, "newsletterId": "", "title": "Social media and networks are the new horsemen of Apocalypse of this century.", "slug": "social-media-and-networks-are-the-new-horsemen-of-apocalypse-of-this-century", "versionId": "a2274817b453", "inResponseToMediaResourceId": "3a040e50cca709732cc42071e7c43389", "isSubscriptionLocked": false, "updatedAt": 1481614704274, "mediumUrl": "", "previewContent": {"bodyModel": {"sections": [{"startIndex": 0}], "paragraphs": [{"text": "Social media and networks are the new horsemen of Apocalypse of this century. Ignoring them at least for a short period increases productivity\u00a0significantly.", "name": "b60f", "alignment": 1, "markups": [], "type": 1}, {"text": "Music. I\u2019ve never tried to work with classical music but I know that metal is a good choice for a background music, while doing just a mechanical work where serious solutions are already accepted and you know the algorithm.", "name": "b3b3", "alignment": 1, "markups": [], "type": 1}]}, "isFullContent": true}, "webCanonicalUrl": "", "notifyFacebook": false, "experimentalCss": "", "virtuals": {"links": {"entries": [], "generatedAt": 1481614703911, "version": "0.3"}, "imageCount": 0, "socialRecommendsCount": 0, "wordCount": 63, "totalClapCount": 0, "responsesCreatedCount": 0, "isLockedPreviewOnly": false, "usersBySocialRecommends": [], "isBookmarked": false, "recommends": 5, "subtitle": "Music. I\u2019ve never tried to work with classical music but I know that metal is a good choice for a background music, while doing just a\u2026", "takeoverId": "", "metaDescription": "", "previewImage": {"originalHeight": 0, "originalWidth": 0, "imageId": "", "height": 0, "filter": "", "width": 0, "strategy": "resample", "backgroundSize": ""}, "readingTime": 0.23773584905660378, "allowNotes": true, "tags": [{"name": "Music", "slug": "music", "metadata": {"coverImage": {"id": "1*IiNmmcwgPtVI77r3VcrGjA.jpeg"}, "postCount": 68386, "followerCount": 626551}, "postCount": 68386, "type": "Tag", "virtuals": {"isFollowing": false}}, {"name": "Productivity", "slug": "productivity", "metadata": {"coverImage": {"id": "1*23EURixTdGzquD9--plvmw.jpeg"}, "postCount": 43269, "followerCount": 896856}, "postCount": 43269, "type": "Tag", "virtuals": {"isFollowing": false}}]}, "allowResponses": true, "homeCollectionId": "", "isSponsored": false, "importedUrl": "", "vote": false, "acceptedAt": 0, "firstPublishedAt": 1481614703514, "approvedHomeCollectionId": "", "type": "Post", "latestRev": 50, "content": {"subtitle": "Music. I\u2019ve never tried to work with classical music but I know that metal is a good choice for a background music, while doing just a\u2026", "postDisplay": {"coverless": true}}, "latestPublishedVersion": "a2274817b453", "hasUnpublishedEdits": false, "notifyTwitter": false, "isApprovedTranslation": false, "creatorId": "e8bf362354a1", "visibility": 0, "translationSourcePostId": "", "latestPublishedAt": 1481614703514, "canonicalUrl": "", "coverless": true, "migrationId": "", "uniqueSlug": "social-media-and-networks-are-the-new-horsemen-of-apocalypse-of-this-century-8303fae9980c", "latestVersion": "a2274817b453", "isSeries": false}, "c697f9fa0b27": {"importedPublishedAt": 0, "inResponseToPostId": "6cb23738f823", "notifyFollowers": true, "seriesLastAppendedAt": 0, "translationSourceCreatorId": "", "displayAuthor": "", "isTitleSynthesized": true, "detectedLanguage": "un", "license": 0, "id": "c697f9fa0b27", "createdAt": 1481582573428, "inResponseToRemovedAt": 0, "isRequestToPubDisabled": false, "responseHiddenOnParentPostAt": 0, "newsletterId": "", "title": "Love It", "slug": "love-it", "versionId": "3a666470c04a", "inResponseToMediaResourceId": "3a040e50cca709732cc42071e7c43389", "isSubscriptionLocked": false, "updatedAt": 1481582577922, "mediumUrl": "", "previewContent": {"bodyModel": {"sections": [{"startIndex": 0}], "paragraphs": [{"text": "Love It", "name": "545d", "alignment": 1, "markups": [], "type": 1}]}, "isFullContent": true}, "webCanonicalUrl": "", "notifyFacebook": false, "experimentalCss": "", "virtuals": {"links": {"entries": [], "generatedAt": 1481582578267, "version": "0.3"}, "imageCount": 0, "socialRecommendsCount": 0, "wordCount": 2, "totalClapCount": 0, "responsesCreatedCount": 1, "isLockedPreviewOnly": false, "usersBySocialRecommends": [], "isBookmarked": false, "recommends": 2, "subtitle": "", "takeoverId": "", "metaDescription": "", "previewImage": {"originalHeight": 0, "originalWidth": 0, "imageId": "", "height": 0, "filter": "", "width": 0, "strategy": "resample", "backgroundSize": ""}, "readingTime": 0.007547169811320755, "allowNotes": true, "tags": []}, "allowResponses": true, "homeCollectionId": "", "isSponsored": false, "importedUrl": "", "vote": false, "acceptedAt": 0, "firstPublishedAt": 1481582577922, "approvedHomeCollectionId": "", "type": "Post", "latestRev": 5, "content": {"postDisplay": {"coverless": true}}, "latestPublishedVersion": "3a666470c04a", "hasUnpublishedEdits": false, "notifyTwitter": false, "isApprovedTranslation": false, "creatorId": "e0c6222c2571", "visibility": 0, "translationSourcePostId": "", "latestPublishedAt": 1481582577922, "canonicalUrl": "", "coverless": true, "migrationId": "", "uniqueSlug": "love-it-c697f9fa0b27", "latestVersion": "3a666470c04a", "isSeries": false}, "3081a4a8f7c0": {"importedPublishedAt": 0, "inResponseToPostId": "6cb23738f823", "notifyFollowers": true, "seriesLastAppendedAt": 0, "translationSourceCreatorId": "", "displayAuthor": "", "isTitleSynthesized": true, "detectedLanguage": "en", "license": 0, "id": "3081a4a8f7c0", "createdAt": 1482680046702, "inResponseToRemovedAt": 0, "isRequestToPubDisabled": false, "responseHiddenOnParentPostAt": 0, "newsletterId": "", "title": "All instruments, breaths, fingers, bodies, brains working together in beautiful patterns.", "slug": "all-instruments-breaths-fingers-bodies-brains-working-together-in-beautiful-patterns", "versionId": "ae0efa52766a", "inResponseToMediaResourceId": "c38bdf91d291cdc3e58068b8dbc5e3c0", "isSubscriptionLocked": false, "updatedAt": 1482680113617, "mediumUrl": "", "previewContent": {"bodyModel": {"sections": [{"startIndex": 0}], "paragraphs": [{"text": "All instruments, breaths, fingers, bodies, brains working together in beautiful patterns. Why\u2026of course this production of frequency and vibration is a Key Of Life! Thank you, sir, for serving up this thought on a silver platter!", "name": "53f4", "alignment": 1, "markups": [], "type": 1}]}, "isFullContent": true}, "webCanonicalUrl": "", "notifyFacebook": false, "experimentalCss": "", "virtuals": {"links": {"entries": [], "generatedAt": 1482680113205, "version": "0.3"}, "imageCount": 0, "socialRecommendsCount": 0, "wordCount": 36, "totalClapCount": 0, "responsesCreatedCount": 0, "isLockedPreviewOnly": false, "usersBySocialRecommends": [], "isBookmarked": false, "recommends": 1, "subtitle": "", "takeoverId": "", "metaDescription": "", "previewImage": {"originalHeight": 0, "originalWidth": 0, "imageId": "", "height": 0, "filter": "", "width": 0, "strategy": "resample", "backgroundSize": ""}, "readingTime": 0.13584905660377358, "allowNotes": true, "tags": []}, "allowResponses": true, "homeCollectionId": "", "isSponsored": false, "importedUrl": "", "vote": false, "acceptedAt": 0, "firstPublishedAt": 1482680112867, "approvedHomeCollectionId": "", "type": "Post", "latestRev": 18, "content": {"postDisplay": {"coverless": true}}, "latestPublishedVersion": "ae0efa52766a", "hasUnpublishedEdits": false, "notifyTwitter": false, "isApprovedTranslation": false, "creatorId": "7fd8b4b65d69", "visibility": 0, "translationSourcePostId": "", "latestPublishedAt": 1482680112867, "canonicalUrl": "", "coverless": true, "migrationId": "", "uniqueSlug": "all-instruments-breaths-fingers-bodies-brains-working-together-in-beautiful-patterns-3081a4a8f7c0", "latestVersion": "ae0efa52766a", "isSeries": false}}, "User": {"12c1710d9a51": {"facebookAccountId": "", "name": "KaZ Cruse Akers", "username": "kazcruseakers", "mediumMemberAt": 0, "userId": "12c1710d9a51", "type": "User", "bio": "", "lastPostCreatedAt": 1483205252935, "imageId": "0*k19UxDrrG3TgBW53.", "backgroundImageId": "", "createdAt": 1463430508583, "twitterScreenName": "", "mediumMemberWaitlistedAt": 0, "allowNotes": 1}, "7fd8b4b65d69": {"facebookAccountId": "", "name": "Mary Holden", "username": "marylholden", "mediumMemberAt": 0, "userId": "7fd8b4b65d69", "type": "User", "bio": "Editor and writer.", "lastPostCreatedAt": 1492148947353, "imageId": "0*CxH6m0eKtCb_z-q_.jpg", "backgroundImageId": "", "createdAt": 1370994635791, "twitterScreenName": "marylholden", "mediumMemberWaitlistedAt": 0, "allowNotes": 1}, "38e4819c46e8": {"facebookAccountId": "10104535126297443", "name": "Hannah G", "username": "hannahgentry", "mediumMemberAt": 0, "userId": "38e4819c46e8", "type": "User", "bio": "", "lastPostCreatedAt": 1481673733115, "imageId": "0*LJMzpP67-k6-8dUz.", "backgroundImageId": "", "createdAt": 1480299148479, "twitterScreenName": "", "mediumMemberWaitlistedAt": 0, "allowNotes": 1}, "74c2db95497c": {"facebookAccountId": "10207393473051627", "name": "Vigil Viswanathan", "username": "vigilviswanathan", "mediumMemberAt": 1490790663000, "userId": "74c2db95497c", "type": "User", "bio": "", "lastPostCreatedAt": 1489412196440, "imageId": "1*GOWJ_B1HofqL1_P9-0N-1g.jpeg", "backgroundImageId": "", "createdAt": 1454377472581, "twitterScreenName": "", "mediumMemberWaitlistedAt": 0, "allowNotes": 1}, "e8bf362354a1": {"facebookAccountId": "", "name": "Andy Gover", "username": "andygo", "mediumMemberAt": 0, "userId": "e8bf362354a1", "type": "User", "bio": "I want to make our dreams real", "lastPostCreatedAt": 1491979703965, "imageId": "1*k9zJPXjnpRgh-Tu7gDbK9w.jpeg", "backgroundImageId": "", "createdAt": 1481197231862, "twitterScreenName": "", "mediumMemberWaitlistedAt": 0, "allowNotes": 1}, "ab0d3aa95c74": {"facebookAccountId": "10210009814149339", "name": "Isabell Springer", "username": "isabellspringer", "mediumMemberAt": 0, "userId": "ab0d3aa95c74", "type": "User", "bio": "Social Change Agent/Fearless Leader/People Lover/Mom @isabellspringer www.berelationshipready.com", "lastPostCreatedAt": 1487858793765, "imageId": "1*1C13fcWTTKv-WNJ0fTQa7Q.jpeg", "backgroundImageId": "", "createdAt": 1474325578575, "twitterScreenName": "IsabellSpringer", "mediumMemberWaitlistedAt": 0, "allowNotes": 1}, "66ffd0314a1a": {"facebookAccountId": "", "name": "Gerhard G\u00f6rlich", "username": "gerji", "mediumMemberAt": 0, "userId": "66ffd0314a1a", "type": "User", "bio": "Software engineer, pragmatic programmer, maker of 1ppm.club. Writing about side projects, learning and productivity. Follow me on Twitter with @gerji", "lastPostCreatedAt": 1491833888776, "imageId": "0*a1wSUqPfEgrEhC-h.jpeg", "backgroundImageId": "", "createdAt": 1478274096566, "twitterScreenName": "gerji", "mediumMemberWaitlistedAt": 0, "allowNotes": 1}, "19236a61f819": {"facebookAccountId": "", "name": "Alison McLennan", "username": "alisonmclennan", "mediumMemberAt": 0, "userId": "19236a61f819", "type": "User", "bio": "Writer and teacher striving toward higher consciousness and mindfulness.", "lastPostCreatedAt": 1487881475951, "imageId": "1*BFsp_kdm6MktIPQv3xwErw.jpeg", "backgroundImageId": "", "createdAt": 1479098969466, "twitterScreenName": "", "mediumMemberWaitlistedAt": 0, "allowNotes": 1}, "28cf1c3158a8": {"facebookAccountId": "1478430325786082", "name": "Michel Rayot", "username": "MichelRayot", "mediumMemberAt": 0, "userId": "28cf1c3158a8", "type": "User", "bio": "", "lastPostCreatedAt": 1492060242716, "imageId": "0*1UdeYyXVJSBeYg50.jpg", "backgroundImageId": "", "createdAt": 1440050426405, "twitterScreenName": "", "mediumMemberWaitlistedAt": 0, "allowNotes": 1}, "9acc337a2cf5": {"facebookAccountId": "10102983577922799", "name": "Zach Mercurio", "username": "ZachMercurio", "mediumMemberAt": 0, "userId": "9acc337a2cf5", "type": "User", "bio": "Empowers purposeful people + purposeful organizations to better our world | www.ZachMercurio.com", "lastPostCreatedAt": 1490721276432, "imageId": "1*yWoCXu7-2xzIyF67UCaV2Q.jpeg", "backgroundImageId": "", "createdAt": 1463846568544, "twitterScreenName": "ZachMercurio", "mediumMemberWaitlistedAt": 0, "allowNotes": 1}, "9b68e37be4c4": {"facebookAccountId": "10209135667049954", "name": "Mark Petersen", "username": "markpetersen", "mediumMemberAt": 0, "userId": "9b68e37be4c4", "type": "User", "bio": "Self proclaimed Spartan World Ambassador, Mountain and Canyon Guide, Honey-Do list master and fledgling wordsmith.", "lastPostCreatedAt": 1484751973780, "imageId": "1*sTsNCO-hvqbxs2ZT-w_gew.jpeg", "backgroundImageId": "", "createdAt": 1466879780921, "twitterScreenName": "", "mediumMemberWaitlistedAt": 0, "allowNotes": 1}, "28573f014ba4": {"facebookAccountId": "10154184195412860", "name": "Ross McFarland", "username": "rossimcf", "mediumMemberAt": 0, "userId": "28573f014ba4", "type": "User", "bio": "", "lastPostCreatedAt": 1482101978505, "imageId": "0*9Te8_h-4z5SQy-XY.", "backgroundImageId": "", "createdAt": 1476041860410, "twitterScreenName": "", "mediumMemberWaitlistedAt": 0, "allowNotes": 1}, "e0c6222c2571": {"facebookAccountId": "951710741571715", "name": "Luis Mercado", "username": "luismercado_5017", "mediumMemberAt": 0, "userId": "e0c6222c2571", "type": "User", "bio": "", "lastPostCreatedAt": 1481582573428, "imageId": "0*mKo9rctftV5CukS0.jpg", "backgroundImageId": "", "createdAt": 1451952687601, "twitterScreenName": "", "mediumMemberWaitlistedAt": 0, "allowNotes": 1}, "e71d494d8acc": {"facebookAccountId": "", "name": "Bill Abrams", "username": "babrams", "mediumMemberAt": 0, "userId": "e71d494d8acc", "type": "User", "bio": "Industry Leading Blockchain Consultant", "lastPostCreatedAt": 1488986663097, "imageId": "1*hr_XccAQr5MqIkc08crD-Q.jpeg", "backgroundImageId": "", "createdAt": 1456227193874, "twitterScreenName": "", "mediumMemberWaitlistedAt": 0, "allowNotes": 1}, "f42556cd052b": {"facebookAccountId": "", "name": "Gabriel Lesz", "username": "GaberLez", "mediumMemberAt": 0, "userId": "f42556cd052b", "type": "User", "bio": "A l\u00f3gica da criatividade \u00e9 o caos bem-aventurado.", "lastPostCreatedAt": 1491408303627, "imageId": "1*_5ZEyp9A6zv3DhiRUBuUPg.jpeg", "backgroundImageId": "", "createdAt": 1434749711331, "twitterScreenName": "GaberLez", "mediumMemberWaitlistedAt": 0, "allowNotes": 1}, "9e04cd18f6c8": {"facebookAccountId": "10207941012416480", "name": "mitzi.flyte", "username": "mitzi.flyte", "mediumMemberAt": 0, "userId": "9e04cd18f6c8", "type": "User", "bio": "", "lastPostCreatedAt": 1491738746167, "imageId": "1*Mlw5R8GVsIqQTPsL2EmzNg.jpeg", "backgroundImageId": "", "createdAt": 1464526384944, "twitterScreenName": "mitziflyte", "mediumMemberWaitlistedAt": 0, "allowNotes": 1}, "b1f6b1234385": {"facebookAccountId": "", "name": "Scott Ferguson", "username": "ScottFerguson7", "mediumMemberAt": 0, "userId": "b1f6b1234385", "type": "User", "bio": "President of Noble Striving Inc. A co. working to change the world for the better by promoting goodthot (R)", "lastPostCreatedAt": 1481646830666, "imageId": "0*d178XLZwyXZ6FZNr.jpg", "backgroundImageId": "", "createdAt": 1451962429876, "twitterScreenName": "ScottFerguson7", "mediumMemberWaitlistedAt": 0, "allowNotes": 1}, "8804c3026cce": {"facebookAccountId": "484771975001632", "name": "Chad Grills", "username": "ChadGrills", "mediumMemberAt": 1491233136000, "userId": "8804c3026cce", "type": "User", "bio": "Founder of www.TheMission.co", "lastPostCreatedAt": 1491926358608, "imageId": "1*LSicRIBRgq99yVSXYYpBjg.png", "backgroundImageId": "1*KOMQs3yyKLfUNttp874GQQ.jpeg", "createdAt": 1384640351560, "twitterScreenName": "ChadGrills", "mediumMemberWaitlistedAt": 1490288603599, "allowNotes": 1}, "24c6d2541429": {"facebookAccountId": "1303812133025201", "name": "Onur Can", "username": "olacaktekrar", "mediumMemberAt": 0, "userId": "24c6d2541429", "type": "User", "bio": "Shitty life with big ideas.", "lastPostCreatedAt": 1482356622431, "imageId": "1*xepgw786zQchf4HSbe6oog.jpeg", "backgroundImageId": "", "createdAt": 1481016453618, "twitterScreenName": "olacaktekrar", "mediumMemberWaitlistedAt": 0, "allowNotes": 1}, "f269f860c9cc": {"facebookAccountId": "", "name": "Mohamed Salah", "username": "mohamedsalahshalaby4", "mediumMemberAt": 0, "userId": "f269f860c9cc", "type": "User", "bio": "", "lastPostCreatedAt": 1481605369151, "imageId": "0*5eK8OOinQZ6ZnsMG.", "backgroundImageId": "", "createdAt": 1477039787397, "twitterScreenName": "", "mediumMemberWaitlistedAt": 0, "allowNotes": 1}, "1bdc591ece16": {"facebookAccountId": "", "name": "Vanessa Mak", "username": "vanessapmak", "mediumMemberAt": 0, "userId": "1bdc591ece16", "type": "User", "bio": "", "lastPostCreatedAt": 1481677663546, "imageId": "0*lZxmCogI1fCUWnCl.", "backgroundImageId": "", "createdAt": 1478623711841, "twitterScreenName": "", "mediumMemberWaitlistedAt": 0, "allowNotes": 1}}, "MediaResource": {"990fdae09f173af24740563e9c6f58dc": {"iframeHeight": 0, "mediumPost": {"postId": "44f7ae1d0822"}, "iframeWidth": 0, "description": "", "thumbnailWidth": 0, "title": "Took the words right out of my mouth.", "mediaResourceId": "990fdae09f173af24740563e9c6f58dc", "display": 1, "domain": "medium.com", "thumbnailHeight": 0, "mediaResourceType": "MediaResourceMediumPost", "thumbnailUrl": "", "authorName": "", "iframeSrc": "", "thumbnailImageId": "", "type": "MediaResource", "href": "https://medium.com/@isabellspringer/took-the-words-right-out-of-my-mouth-44f7ae1d0822"}, "d8acc612b38bdf75c352703b1420074c": {"iframeHeight": 0, "mediumPost": {"postId": "c697f9fa0b27"}, "iframeWidth": 0, "description": "", "thumbnailWidth": 0, "title": "Love It", "mediaResourceId": "d8acc612b38bdf75c352703b1420074c", "display": 1, "domain": "medium.com", "thumbnailHeight": 0, "mediaResourceType": "MediaResourceMediumPost", "thumbnailUrl": "", "authorName": "", "iframeSrc": "", "thumbnailImageId": "", "type": "MediaResource", "href": "https://medium.com/@luismercado_5017/love-it-c697f9fa0b27"}, "3a040e50cca709732cc42071e7c43389": {"iframeHeight": 0, "mediumPost": {"postId": "6cb23738f823"}, "iframeWidth": 0, "description": "", "thumbnailWidth": 1600, "title": "Social media fasts, brain boosters, soundtracks that increase attention, and real friendships", "mediaResourceId": "3a040e50cca709732cc42071e7c43389", "display": 1, "domain": "medium.com", "thumbnailHeight": 1200, "mediaResourceType": "MediaResourceMediumPost", "thumbnailUrl": "", "authorName": "", "iframeSrc": "", "thumbnailImageId": "0*0FeeeJGWp3n8ybP0.", "type": "MediaResource", "href": "https://medium.com/the-mission/social-media-fasts-brain-boosters-soundtracks-that-increase-attention-and-real-friendships-6cb23738f823"}, "e90896d934f9f0eac32d13cbe577934a": {"iframeHeight": 0, "mediumPost": {"postId": "e9482caf67be"}, "iframeWidth": 0, "description": "", "thumbnailWidth": 0, "title": "Thank you.", "mediaResourceId": "e90896d934f9f0eac32d13cbe577934a", "display": 1, "domain": "medium.com", "thumbnailHeight": 0, "mediaResourceType": "MediaResourceMediumPost", "thumbnailUrl": "", "authorName": "", "iframeSrc": "", "thumbnailImageId": "", "type": "MediaResource", "href": "https://medium.com/@mitzi.flyte/thank-you-e9482caf67be"}, "f03c0ad0e37a47b675da6ce41f07a38a": {"iframeHeight": 0, "mediumPost": {"postId": "6cb23738f823"}, "iframeWidth": 0, "description": "", "thumbnailWidth": 1600, "title": "Social media fasts, brain boosters, soundtracks that increase attention, and real friendships", "mediaResourceId": "f03c0ad0e37a47b675da6ce41f07a38a", "display": 1, "domain": "medium.com", "thumbnailHeight": 1200, "mediaResourceType": "MediaResourceMediumQuote", "thumbnailUrl": "", "authorName": "", "iframeSrc": "", "thumbnailImageId": "0*0FeeeJGWp3n8ybP0.", "type": "MediaResource", "href": "https://medium.com/the-mission/social-media-fasts-brain-boosters-soundtracks-that-increase-attention-and-real-friendships-6cb23738f823#ecab--highlight-616607a75b7a", "mediumQuote": {"quoteId": "616607a75b7a"}}, "c38bdf91d291cdc3e58068b8dbc5e3c0": {"iframeHeight": 0, "mediumPost": {"postId": "6cb23738f823"}, "iframeWidth": 0, "description": "", "thumbnailWidth": 1600, "title": "Social media fasts, brain boosters, soundtracks that increase attention, and real friendships", "mediaResourceId": "c38bdf91d291cdc3e58068b8dbc5e3c0", "display": 1, "domain": "medium.com", "thumbnailHeight": 1200, "mediaResourceType": "MediaResourceMediumQuote", "thumbnailUrl": "", "authorName": "", "iframeSrc": "", "thumbnailImageId": "0*0FeeeJGWp3n8ybP0.", "type": "MediaResource", "href": "https://medium.com/the-mission/social-media-fasts-brain-boosters-soundtracks-that-increase-attention-and-real-friendships-6cb23738f823#6a00--highlight-87e7540e2b86", "mediumQuote": {"quoteId": "87e7540e2b86"}}}}, "paging": {"path": "/_/api/posts/6cb23738f823/responsesStream", "next": {"to": "0:eb8311aeb9e6", "limit": 25}}, "streamItems": [{"randomId": "13a5e42d7412", "postPreview": {"postId": "8303fae9980c"}, "itemType": "postPreview", "type": "StreamItem", "createdAt": 1492169253925}, {"randomId": "399ec7437529", "type": "StreamItem", "itemType": "conversation", "conversation": {"userIds": ["9e04cd18f6c8", "8804c3026cce"], "conversationItems": [{"postSuggestionReasons": [{"reason": 31, "users": [{"name": "Chad Grills", "username": "ChadGrills", "userId": "8804c3026cce", "image": {"imageId": "1*LSicRIBRgq99yVSXYYpBjg.png"}}]}], "postId": "e9482caf67be", "displayMode": 1}, {"postSuggestionReasons": [{"reason": 29}], "postId": "c8cba35f08da", "displayMode": 1}]}, "createdAt": 1492169253925}, {"randomId": "f88b67e6c779", "type": "StreamItem", "itemType": "conversation", "conversation": {"userIds": ["ab0d3aa95c74", "8804c3026cce"], "conversationItems": [{"postSuggestionReasons": [{"reason": 31, "users": [{"name": "Chad Grills", "username": "ChadGrills", "userId": "8804c3026cce", "image": {"imageId": "1*LSicRIBRgq99yVSXYYpBjg.png"}}]}], "postId": "44f7ae1d0822", "displayMode": 1}, {"postSuggestionReasons": [{"reason": 29}], "postId": "46834d8d6e2c", "displayMode": 1}]}, "createdAt": 1492169253925}, {"randomId": "242a3c526257", "postPreview": {"postId": "f294f1e6e51b"}, "itemType": "postPreview", "type": "StreamItem", "createdAt": 1492169253925}, {"randomId": "5468aa9a9775", "type": "StreamItem", "itemType": "conversation", "conversation": {"userIds": ["e0c6222c2571", "8804c3026cce"], "conversationItems": [{"postSuggestionReasons": [{"reason": 31, "users": [{"name": "Chad Grills", "username": "ChadGrills", "userId": "8804c3026cce", "image": {"imageId": "1*LSicRIBRgq99yVSXYYpBjg.png"}}]}], "postId": "c697f9fa0b27", "displayMode": 1}, {"postSuggestionReasons": [{"reason": 29}], "postId": "67a15fd0d2d2", "displayMode": 1}]}, "createdAt": 1492169253925}, {"randomId": "e5572043040e", "postPreview": {"postId": "59e8c79700b9"}, "itemType": "postPreview", "type": "StreamItem", "createdAt": 1492169253925}, {"randomId": "bf1515c239b0", "postPreview": {"postId": "174139bb34f4"}, "itemType": "postPreview", "type": "StreamItem", "createdAt": 1492169253925}, {"randomId": "d2ae6b6ff8b0", "postPreview": {"postId": "b47aa27ced51"}, "itemType": "postPreview", "type": "StreamItem", "createdAt": 1492169253925}, {"randomId": "1a62ca20a32b", "postPreview": {"postId": "a38c34a21857"}, "itemType": "postPreview", "type": "StreamItem", "createdAt": 1492169253926}, {"randomId": "d73241bc13ad", "postPreview": {"postId": "9f212d2f109c"}, "itemType": "postPreview", "type": "StreamItem", "createdAt": 1492169253926}, {"randomId": "6a6b5baa5a3c", "postPreview": {"postId": "9cae348bdef4"}, "itemType": "postPreview", "type": "StreamItem", "createdAt": 1492169253926}, {"randomId": "63c62e3f02cd", "postPreview": {"postId": "92594c93d960"}, "itemType": "postPreview", "type": "StreamItem", "createdAt": 1492169253926}, {"randomId": "586fd016548c", "postPreview": {"postId": "81f61f80e512"}, "itemType": "postPreview", "type": "StreamItem", "createdAt": 1492169253926}, {"randomId": "b480e6c5b15a", "postPreview": {"postId": "7436cd84936b"}, "itemType": "postPreview", "type": "StreamItem", "createdAt": 1492169253926}, {"randomId": "41a27deb8071", "postPreview": {"postId": "640c6d779e0e"}, "itemType": "postPreview", "type": "StreamItem", "createdAt": 1492169253926}, {"randomId": "c01293afd310", "postPreview": {"postId": "50e37e144fe3"}, "itemType": "postPreview", "type": "StreamItem", "createdAt": 1492169253926}, {"randomId": "40434fa831f3", "postPreview": {"postId": "433822f756d"}, "itemType": "postPreview", "type": "StreamItem", "createdAt": 1492169253926}, {"randomId": "1a2939480ff2", "postPreview": {"postId": "3081a4a8f7c0"}, "itemType": "postPreview", "type": "StreamItem", "createdAt": 1492169253926}, {"randomId": "a968e771d848", "postPreview": {"postId": "ee986bfd78e0"}, "itemType": "postPreview", "type": "StreamItem", "createdAt": 1492169253926}, {"randomId": "985277b576de", "postPreview": {"postId": "eb8311aeb9e6"}, "itemType": "postPreview", "type": "StreamItem", "createdAt": 1492169253926}]}, "success": true}