{"b": "28586-6143d83", "v": 3, "payload": {"references": {"Collection": {"d1394cab509e": {"facebookPageName": "artmapinc", "description": "only you can define fitness. #BodyAndMind", "instantArticlesState": 0, "ampLogo": {"originalHeight": 0, "originalWidth": 0, "imageId": "", "height": 0, "filter": "", "width": 0, "strategy": "resample", "backgroundSize": ""}, "favicon": {"originalHeight": 8346, "originalWidth": 8346, "imageId": "1*Sa8v6bYh4YS1vWBeBP7gxg.jpeg", "height": 0, "filter": "", "width": 0, "strategy": "resample", "backgroundSize": ""}, "name": "Fit Yourself Club", "image": {"originalHeight": 8346, "originalWidth": 8346, "imageId": "1*Sa8v6bYh4YS1vWBeBP7gxg.jpeg", "height": 0, "filter": "", "width": 0, "strategy": "resample", "backgroundSize": ""}, "tintColor": "#FFD60B51", "lightText": true, "header": {"layout": 5, "description": "only you can define fitness. #BodyAndMind", "alignment": 2, "title": "", "logoImage": {"originalHeight": 432, "originalWidth": 3600, "alt": "Fit Yourself Club", "id": "1*DmAtDvdcuBKFfzhoxtWupg@2x.png"}, "backgroundImage": {}}, "googleAnalyticsId": "UA-91491383-1", "navItems": [{"title": "Get Fit", "source": "tagSlug", "tagSlug": "fitness", "url": "https://fityourself.club/tagged/fitness", "type": 1}, {"title": "Eat Right", "source": "tagSlug", "tagSlug": "food", "url": "https://fityourself.club/tagged/food", "type": 1}, {"title": "Stay Healthy", "source": "tagSlug", "tagSlug": "health", "url": "https://fityourself.club/tagged/health", "type": 1}, {"title": "Always Be Improving", "source": "tagSlug", "tagSlug": "self-improvement", "url": "https://fityourself.club/tagged/self-improvement", "type": 1}, {"title": "Life Lessons", "source": "tagSlug", "tagSlug": "life-lessons", "url": "https://fityourself.club/tagged/life-lessons", "type": 1}, {"title": "Fitness Trends", "url": "https://fityourself.club/trending", "type": 3}], "publicEmail": "team@c.how", "type": "Collection", "logo": {"originalHeight": 117, "originalWidth": 980, "imageId": "1*2GPCffx224Mx-6b8lFGSHg.png", "height": 0, "filter": "", "width": 0, "strategy": "resample", "backgroundSize": ""}, "shortDescription": "only you can define fitness. #BodyAndMind", "creatorId": "3ba40c3346c4", "colorBehavior": 2, "slug": "fit-yourself", "tags": ["HEALTH", "FITNESS", "WEIGHT LOSS", "GYM", "FITNESS APPS"], "metadata": {"postCount": 11, "activeAt": 1492109329611, "followerCount": 19756}, "collectionMastheadId": "da038460ff81", "sections": [{"collectionHeaderMetadata": {"layout": 5, "description": "only you can define fitness. #BodyAndMind", "alignment": 2, "title": "", "logoImage": {"originalHeight": 432, "originalWidth": 3600, "alt": "Fit Yourself Club", "id": "1*DmAtDvdcuBKFfzhoxtWupg@2x.png"}, "backgroundImage": {}}, "type": 2}, {"postListMetadata": {"number": 4, "source": 3, "layout": 3, "postIds": ["e18df45582c1", "63c10d113246", "4ef77f04543", "f8eaf66edac7"]}, "type": 1}, {"postListMetadata": {"number": 2, "source": 2, "layout": 5, "postIds": []}, "type": 1}, {"postListMetadata": {"number": 2, "source": 2, "layout": 3, "postIds": []}, "type": 1}, {"postListMetadata": {"number": 8, "source": 1, "layout": 1, "sectionHeader": "The Latest on FitYourself.Club", "postIds": []}, "type": 1}, {"postListMetadata": {"number": 7, "source": 1, "layout": 7, "postIds": []}, "type": 1}, {"postListMetadata": {"number": 4, "source": 3, "layout": 1, "postIds": ["dfa76686ab4b", "fc64a8018110", "6f1d9fdcb307", "8b8afc689a2f"]}, "type": 1}, {"postListMetadata": {"number": 4, "source": 1, "layout": 1, "sectionHeader": "wake up. kick ass. sleep soundly. repeat.", "postIds": []}, "type": 1}, {"postListMetadata": {"number": 4, "source": 2, "layout": 1, "postIds": []}, "type": 1}, {"postListMetadata": {"number": 7, "source": 1, "layout": 7, "postIds": []}, "type": 1}, {"postListMetadata": {"number": 6, "source": 2, "layout": 2, "postIds": []}, "type": 1}, {"postListMetadata": {"number": 24, "source": 1, "layout": 2, "sectionHeader": "wake up. kick ass. sleep soundly. repeat.", "postIds": []}, "type": 1}], "id": "d1394cab509e", "domain": "fityourself.club", "twitterUsername": "fityourselfclub", "colorPalette": {"defaultBackgroundSpectrum": {"colorPoints": [{"point": 0, "color": "#FFEA255E"}, {"point": 0.1, "color": "#FFD82859"}, {"point": 0.2, "color": "#FFC62A53"}, {"point": 0.3, "color": "#FFB42B4C"}, {"point": 0.4, "color": "#FFA22A46"}, {"point": 0.5, "color": "#FF8F283F"}, {"point": 0.6, "color": "#FF7C2538"}, {"point": 0.7, "color": "#FF692130"}, {"point": 0.8, "color": "#FF561C27"}, {"point": 0.9, "color": "#FF42161E"}, {"point": 1, "color": "#FF2D0E13"}], "backgroundColor": "#FFFFFFFF"}, "highlightSpectrum": {"colorPoints": [{"point": 0, "color": "#FFFFDDE4"}, {"point": 0.1, "color": "#FFFFD7E0"}, {"point": 0.2, "color": "#FFFFD1DC"}, {"point": 0.3, "color": "#FFFFCBD8"}, {"point": 0.4, "color": "#FFFFC5D4"}, {"point": 0.5, "color": "#FFFFBED0"}, {"point": 0.6, "color": "#FFFFB8CC"}, {"point": 0.7, "color": "#FFFFB1C7"}, {"point": 0.8, "color": "#FFFFAAC3"}, {"point": 0.9, "color": "#FFFFA4BF"}, {"point": 1, "color": "#FFFF9CBB"}], "backgroundColor": "#FFFFFFFF"}, "tintBackgroundSpectrum": {"colorPoints": [{"point": 0, "color": "#FFD60B51"}, {"point": 0.1, "color": "#FFE63461"}, {"point": 0.2, "color": "#FFF34E72"}, {"point": 0.3, "color": "#FFFF6582"}, {"point": 0.4, "color": "#FFFF7A93"}, {"point": 0.5, "color": "#FFFF8EA3"}, {"point": 0.6, "color": "#FFFFA2B3"}, {"point": 0.7, "color": "#FFFFB5C3"}, {"point": 0.8, "color": "#FFFFC8D3"}, {"point": 0.9, "color": "#FFFFDBE3"}, {"point": 1, "color": "#FFFFEDF3"}], "backgroundColor": "#FFD60B51"}}, "acceleratedMobilePagesState": 0, "virtuals": {"isSubscribed": false, "permissions": {"canAddWriters": false, "canSubmit": false, "canEditOwnPosts": false, "canSendNewsletter": false, "canBeAssignedAuthor": false, "canRepublish": false, "canManageAll": false, "canViewLockedPosts": false, "canRemove": false, "canPublishAll": false, "canViewCloaked": false, "canEditPosts": false, "canPublish": false, "canViewStats": false}, "isNewsletterSubscribed": false, "memberOfMembershipPlanId": ""}}}, "Post": {"7aa0007937ea": {"importedPublishedAt": 0, "inResponseToPostId": "ebba9dbd4151", "notifyFollowers": true, "seriesLastAppendedAt": 0, "translationSourceCreatorId": "", "displayAuthor": "", "isTitleSynthesized": true, "detectedLanguage": "en", "license": 0, "id": "7aa0007937ea", "createdAt": 1489657058553, "inResponseToRemovedAt": 0, "isRequestToPubDisabled": false, "responseHiddenOnParentPostAt": 0, "newsletterId": "", "title": "Loved this.", "slug": "loved-this", "versionId": "c6ca6aad99d4", "inResponseToMediaResourceId": "f9ded0f166c9e50463d59f4c25162e19", "isSubscriptionLocked": false, "updatedAt": 1489657142621, "mediumUrl": "", "previewContent": {"bodyModel": {"sections": [{"startIndex": 0}], "paragraphs": [{"text": "Loved this. Its difficult to come to 7 reasons out of the hundreds that could be there, but these seven do justice to the intent.", "name": "a274", "alignment": 1, "markups": [], "type": 1}]}, "isFullContent": true}, "webCanonicalUrl": "", "notifyFacebook": false, "experimentalCss": "", "virtuals": {"links": {"entries": [], "generatedAt": 1489657142976, "version": "0.3"}, "imageCount": 0, "socialRecommendsCount": 0, "wordCount": 25, "totalClapCount": 0, "responsesCreatedCount": 0, "isLockedPreviewOnly": false, "usersBySocialRecommends": [], "isBookmarked": false, "recommends": 0, "subtitle": "", "takeoverId": "", "metaDescription": "", "previewImage": {"originalHeight": 0, "originalWidth": 0, "imageId": "", "height": 0, "filter": "", "width": 0, "strategy": "resample", "backgroundSize": ""}, "readingTime": 0.09433962264150944, "allowNotes": true, "tags": []}, "allowResponses": true, "homeCollectionId": "", "isSponsored": false, "importedUrl": "", "vote": false, "acceptedAt": 0, "firstPublishedAt": 1489657142621, "approvedHomeCollectionId": "", "type": "Post", "latestRev": 18, "content": {"postDisplay": {"coverless": true}}, "latestPublishedVersion": "c6ca6aad99d4", "hasUnpublishedEdits": false, "notifyTwitter": false, "isApprovedTranslation": false, "creatorId": "3202033d1a97", "visibility": 0, "translationSourcePostId": "", "latestPublishedAt": 1489657142621, "canonicalUrl": "", "coverless": true, "migrationId": "", "uniqueSlug": "loved-this-7aa0007937ea", "latestVersion": "c6ca6aad99d4", "isSeries": false}, "ebba9dbd4151": {"importedPublishedAt": 0, "inResponseToPostId": "", "notifyFollowers": true, "seriesLastAppendedAt": 0, "translationSourceCreatorId": "", "displayAuthor": "", "isTitleSynthesized": true, "detectedLanguage": "en", "license": 0, "id": "ebba9dbd4151", "createdAt": 1489518495025, "inResponseToRemovedAt": 0, "isRequestToPubDisabled": false, "responseHiddenOnParentPostAt": 0, "newsletterId": "", "title": "Reading Is For Geeks? Wrong, It\u2019s for Achievers.", "slug": "reading-is-for-geeks-wrong-its-for-achievers", "versionId": "20e722f22f31", "inResponseToMediaResourceId": "", "isSubscriptionLocked": false, "updatedAt": 1489581896191, "mediumUrl": "", "previewContent": {"bodyModel": {"sections": [{"startIndex": 0}], "paragraphs": [{"text": "Reading Is For Geeks? Wrong, It\u2019s for Achievers.", "name": "52d6", "alignment": 1, "markups": [], "type": 3}, {"text": "7 Reasons why Mark Zuckerberg, Oprah, Bill Gates, Elon Musk, and co. spend hours every day reading\u2026", "name": "34bf", "alignment": 1, "markups": [], "type": 13}]}, "isFullContent": false}, "webCanonicalUrl": "http://www.njlifehacks.com/read-more/", "notifyFacebook": false, "experimentalCss": "", "virtuals": {"links": {"entries": [{"alts": [{"url": "https://cdn.ampproject.org/c/s/amp.businessinsider.com/elon-musk-favorite-books-2015-10", "type": 1}], "url": "http://www.businessinsider.com/elon-musk-favorite-books-2015-10"}, {"alts": [{"url": "https://cdn.ampproject.org/c/s/amp.businessinsider.com/warren-buffett-oprah-winfrey-and-bill-gates-all-share-this-pastime-2015-3", "type": 1}], "url": "http://www.businessinsider.com/warren-buffett-oprah-winfrey-and-bill-gates-all-share-this-pastime-2015-3"}, {"alts": [{"url": "https://cdn.ampproject.org/c/s/amp.businessinsider.com/bill-gates-habit-common-among-successful-people-2016-1", "type": 1}], "url": "http://www.businessinsider.com/bill-gates-habit-common-among-successful-people-2016-1"}, {"alts": [{"url": "https://cdn.ampproject.org/c/s/amp.businessinsider.com/why-bill-gates-reads-50-books-a-year-2015-11", "type": 1}], "url": "http://www.businessinsider.com/why-bill-gates-reads-50-books-a-year-2015-11"}, {"alts": [{"url": "https://cdn.ampproject.org/c/blogmaverick.com/2007/12/24/success-and-motivation/amp/", "type": 1}], "url": "http://blogmaverick.com/2007/12/24/success-and-motivation/"}, {"alts": [{"url": "https://cdn.ampproject.org/c/amp.usatoday.com/story/14447531/", "type": 1}], "url": "http://www.usatoday.com/story/money/personalfinance/2014/08/24/peculiar-habits-of-successful-people/14447531/"}], "generatedAt": 1489519189417, "version": "0.3"}, "imageCount": 4, "tags": [{"name": "Books", "slug": "books", "metadata": {"coverImage": {"id": "1*-djakoQnr4pNRTlE6R92_g.jpeg"}, "postCount": 36110, "followerCount": 763301}, "postCount": 36110, "type": "Tag", "virtuals": {"isFollowing": false}}, {"name": "Life", "slug": "life", "metadata": {"coverImage": {"id": "1*0sJtn9WT-yfCMX8S8LyYVg.jpeg"}, "postCount": 136533, "followerCount": 957515}, "postCount": 136533, "type": "Tag", "virtuals": {"isFollowing": false}}, {"name": "Life Lessons", "slug": "life-lessons", "metadata": {"coverImage": {"id": "1*xJV8uYsDYrnDwulfbMByRQ.jpeg"}, "postCount": 121967, "followerCount": 960219}, "postCount": 121967, "type": "Tag", "virtuals": {"isFollowing": false}}, {"name": "Personal Development", "slug": "personal-development", "metadata": {"coverImage": {"originalHeight": 2392, "originalWidth": 4287, "isFeatured": true, "id": "1*Sqb7pTtbgxeOgbgJDVGj7w.jpeg"}, "postCount": 21807, "followerCount": 11639}, "postCount": 21807, "type": "Tag", "virtuals": {"isFollowing": false}}, {"name": "Personal Growth", "slug": "personal-growth", "metadata": {"coverImage": {"originalHeight": 3519, "originalWidth": 5279, "id": "1*Lgn3ugKUsbMKkue5t2WwgA.jpeg"}, "postCount": 8103, "followerCount": 1872}, "postCount": 8103, "type": "Tag", "virtuals": {"isFollowing": false}}], "wordCount": 3950, "socialRecommendsCount": 0, "responsesCreatedCount": 1, "isLockedPreviewOnly": false, "usersBySocialRecommends": [], "isBookmarked": false, "publishedInCount": 1, "subtitle": "7 Reasons why Mark Zuckerberg, Oprah, Bill Gates, Elon Musk, and co. spend hours every day reading\u2026", "takeoverId": "", "metaDescription": "", "previewImage": {"originalHeight": 667, "originalWidth": 1000, "imageId": "1*GGqN9eWyG-8kIvSIVVhe9A.jpeg", "height": 0, "filter": "", "width": 0, "strategy": "resample", "backgroundSize": ""}, "totalClapCount": 0, "readingTime": 15.60566037735849, "recommends": 11, "statusForCollection": "APPROVED", "allowNotes": true}, "allowResponses": true, "homeCollectionId": "d1394cab509e", "isSponsored": false, "importedUrl": "http://www.njlifehacks.com/read-more/", "vote": false, "acceptedAt": 0, "firstPublishedAt": 1489519185331, "approvedHomeCollectionId": "d1394cab509e", "type": "Post", "latestRev": 276, "content": {"subtitle": "7 Reasons why Mark Zuckerberg, Oprah, Bill Gates, Elon Musk, and co. spend hours every day reading\u2026", "postDisplay": {"coverless": true}}, "latestPublishedVersion": "20e722f22f31", "hasUnpublishedEdits": false, "notifyTwitter": false, "isApprovedTranslation": false, "creatorId": "dfc5799090b8", "visibility": 0, "translationSourcePostId": "", "latestPublishedAt": 1489519185331, "canonicalUrl": "", "coverless": true, "migrationId": "", "uniqueSlug": "reading-is-for-geeks-wrong-its-for-achievers-ebba9dbd4151", "latestVersion": "20e722f22f31", "isSeries": false}}, "User": {"dfc5799090b8": {"facebookAccountId": "10208954394191621", "name": "Nils Salzgeber", "username": "nilssalzgeber", "mediumMemberAt": 0, "userId": "dfc5799090b8", "type": "User", "bio": "Looking to live a great life. Sharing everything I learn along the way at http://www.njlifehacks.com", "lastPostCreatedAt": 1489518495025, "imageId": "0*4_GUN60T7ihLMnc3.", "backgroundImageId": "", "createdAt": 1463047865611, "twitterScreenName": "", "mediumMemberWaitlistedAt": 0, "allowNotes": 1}, "3202033d1a97": {"facebookAccountId": "965583850184681", "name": "Anjali S Nair", "username": "anjalibonafide", "mediumMemberAt": 0, "userId": "3202033d1a97", "type": "User", "bio": "24. In pursuit of a silver lining. In books; Untold Stories; Singing; In People; Life; Sometimes during the day, I pretend to be a front end engineer too.", "lastPostCreatedAt": 1491429083588, "imageId": "1*s_HBrKC5VqekZvswiisBtw.jpeg", "backgroundImageId": "", "createdAt": 1458738074580, "twitterScreenName": "", "mediumMemberWaitlistedAt": 0, "allowNotes": 1}}, "MediaResource": {"f9ded0f166c9e50463d59f4c25162e19": {"iframeHeight": 0, "mediumPost": {"postId": "ebba9dbd4151"}, "iframeWidth": 0, "description": "", "thumbnailWidth": 1000, "title": "Reading Is For Geeks? Wrong, It\u2019s for Achievers.", "mediaResourceId": "f9ded0f166c9e50463d59f4c25162e19", "display": 1, "domain": "fityourself.club", "thumbnailHeight": 667, "mediaResourceType": "MediaResourceMediumPost", "thumbnailUrl": "", "authorName": "", "iframeSrc": "", "thumbnailImageId": "1*GGqN9eWyG-8kIvSIVVhe9A.jpeg", "type": "MediaResource", "href": "https://fityourself.club/reading-is-for-geeks-wrong-its-for-achievers-ebba9dbd4151"}}}, "paging": {}, "streamItems": [{"randomId": "d7e5ece056b0", "postPreview": {"postId": "7aa0007937ea"}, "itemType": "postPreview", "type": "StreamItem", "createdAt": 1492155577863}]}, "success": true}